{
  "archives": [
    {
      "archive_item_identifier": "pr3-2025-06-10",
      "audio_url": "https://archive.org/download/pr3-2025-06-10/pr3_2025-06-10T22-00-00Z.ogg",
      "completeness_ratio": 1.0,
      "day": 11,
      "download_url": "https://archive.org/download/pr3-2025-06-10/pr3_2025-06-10T22-00-00Z.ogg",
      "duration_seconds": 3610.016,
      "hour": 0,
      "hourly_archive_id": 33560,
      "local_date_label": "11.06.2025",
      "local_hour_label": "00:00",
      "local_label": "2025-06-11 00:00 czasu polskiego",
      "local_started_at": "2025-06-11T00:00:00+02:00",
      "local_timezone_label": "czasu polskiego",
      "month": 6,
      "published_at": "2026-05-01T10:43:59.914057+00:00",
      "published_local_label": "2026-05-01 12:43 czasu polskiego",
      "remote_filename": "pr3_2025-06-10T22-00-00Z.ogg",
      "station_slug": "pr3",
      "status": "published",
      "utc_label": "2025-06-10 22:00 UTC",
      "utc_started_at": "2025-06-10T22:00:00+00:00",
      "year": 2025
    },
    {
      "archive_item_identifier": "pr3-2025-06-10",
      "audio_url": "https://archive.org/download/pr3-2025-06-10/pr3_2025-06-10T23-00-00Z.ogg",
      "completeness_ratio": 1.0,
      "day": 11,
      "download_url": "https://archive.org/download/pr3-2025-06-10/pr3_2025-06-10T23-00-00Z.ogg",
      "duration_seconds": 3610.003,
      "hour": 1,
      "hourly_archive_id": 33561,
      "local_date_label": "11.06.2025",
      "local_hour_label": "01:00",
      "local_label": "2025-06-11 01:00 czasu polskiego",
      "local_started_at": "2025-06-11T01:00:00+02:00",
      "local_timezone_label": "czasu polskiego",
      "month": 6,
      "published_at": "2026-05-01T10:43:56.197471+00:00",
      "published_local_label": "2026-05-01 12:43 czasu polskiego",
      "remote_filename": "pr3_2025-06-10T23-00-00Z.ogg",
      "station_slug": "pr3",
      "status": "published",
      "utc_label": "2025-06-10 23:00 UTC",
      "utc_started_at": "2025-06-10T23:00:00+00:00",
      "year": 2025
    },
    {
      "archive_item_identifier": "pr3-2025-06-11",
      "audio_url": "https://archive.org/download/pr3-2025-06-11/pr3_2025-06-11T00-00-00Z.ogg",
      "completeness_ratio": 1.0,
      "day": 11,
      "download_url": "https://archive.org/download/pr3-2025-06-11/pr3_2025-06-11T00-00-00Z.ogg",
      "duration_seconds": 3610.001,
      "hour": 2,
      "hourly_archive_id": 33565,
      "local_date_label": "11.06.2025",
      "local_hour_label": "02:00",
      "local_label": "2025-06-11 02:00 czasu polskiego",
      "local_started_at": "2025-06-11T02:00:00+02:00",
      "local_timezone_label": "czasu polskiego",
      "month": 6,
      "published_at": "2026-05-01T10:38:54.183859+00:00",
      "published_local_label": "2026-05-01 12:38 czasu polskiego",
      "remote_filename": "pr3_2025-06-11T00-00-00Z.ogg",
      "station_slug": "pr3",
      "status": "published",
      "utc_label": "2025-06-11 00:00 UTC",
      "utc_started_at": "2025-06-11T00:00:00+00:00",
      "year": 2025
    },
    {
      "archive_item_identifier": "pr3-2025-06-11",
      "audio_url": "https://archive.org/download/pr3-2025-06-11/pr3_2025-06-11T01-00-00Z.ogg",
      "completeness_ratio": 1.0,
      "day": 11,
      "download_url": "https://archive.org/download/pr3-2025-06-11/pr3_2025-06-11T01-00-00Z.ogg",
      "duration_seconds": 3610.008,
      "hour": 3,
      "hourly_archive_id": 33566,
      "local_date_label": "11.06.2025",
      "local_hour_label": "03:00",
      "local_label": "2025-06-11 03:00 czasu polskiego",
      "local_started_at": "2025-06-11T03:00:00+02:00",
      "local_timezone_label": "czasu polskiego",
      "month": 6,
      "published_at": "2026-05-01T10:38:56.417236+00:00",
      "published_local_label": "2026-05-01 12:38 czasu polskiego",
      "remote_filename": "pr3_2025-06-11T01-00-00Z.ogg",
      "station_slug": "pr3",
      "status": "published",
      "utc_label": "2025-06-11 01:00 UTC",
      "utc_started_at": "2025-06-11T01:00:00+00:00",
      "year": 2025
    },
    {
      "archive_item_identifier": "pr3-2025-06-11",
      "audio_url": "https://archive.org/download/pr3-2025-06-11/pr3_2025-06-11T02-00-00Z.ogg",
      "completeness_ratio": 1.0,
      "day": 11,
      "download_url": "https://archive.org/download/pr3-2025-06-11/pr3_2025-06-11T02-00-00Z.ogg",
      "duration_seconds": 3610.015,
      "hour": 4,
      "hourly_archive_id": 33570,
      "local_date_label": "11.06.2025",
      "local_hour_label": "04:00",
      "local_label": "2025-06-11 04:00 czasu polskiego",
      "local_started_at": "2025-06-11T04:00:00+02:00",
      "local_timezone_label": "czasu polskiego",
      "month": 6,
      "published_at": "2026-05-01T10:39:45.924738+00:00",
      "published_local_label": "2026-05-01 12:39 czasu polskiego",
      "remote_filename": "pr3_2025-06-11T02-00-00Z.ogg",
      "station_slug": "pr3",
      "status": "published",
      "utc_label": "2025-06-11 02:00 UTC",
      "utc_started_at": "2025-06-11T02:00:00+00:00",
      "year": 2025
    },
    {
      "archive_item_identifier": "pr3-2025-06-11",
      "audio_url": "https://archive.org/download/pr3-2025-06-11/pr3_2025-06-11T03-00-00Z.ogg",
      "completeness_ratio": 1.0,
      "day": 11,
      "download_url": "https://archive.org/download/pr3-2025-06-11/pr3_2025-06-11T03-00-00Z.ogg",
      "duration_seconds": 3610.0,
      "hour": 5,
      "hourly_archive_id": 33571,
      "local_date_label": "11.06.2025",
      "local_hour_label": "05:00",
      "local_label": "2025-06-11 05:00 czasu polskiego",
      "local_started_at": "2025-06-11T05:00:00+02:00",
      "local_timezone_label": "czasu polskiego",
      "month": 6,
      "published_at": "2026-05-01T10:39:48.202912+00:00",
      "published_local_label": "2026-05-01 12:39 czasu polskiego",
      "remote_filename": "pr3_2025-06-11T03-00-00Z.ogg",
      "station_slug": "pr3",
      "status": "published",
      "utc_label": "2025-06-11 03:00 UTC",
      "utc_started_at": "2025-06-11T03:00:00+00:00",
      "year": 2025
    },
    {
      "archive_item_identifier": "pr3-2025-06-11",
      "audio_url": "https://archive.org/download/pr3-2025-06-11/pr3_2025-06-11T04-00-00Z.ogg",
      "completeness_ratio": 1.0,
      "day": 11,
      "download_url": "https://archive.org/download/pr3-2025-06-11/pr3_2025-06-11T04-00-00Z.ogg",
      "duration_seconds": 3610.016,
      "hour": 6,
      "hourly_archive_id": 33575,
      "local_date_label": "11.06.2025",
      "local_hour_label": "06:00",
      "local_label": "2025-06-11 06:00 czasu polskiego",
      "local_started_at": "2025-06-11T06:00:00+02:00",
      "local_timezone_label": "czasu polskiego",
      "month": 6,
      "published_at": "2026-05-01T10:40:39.238342+00:00",
      "published_local_label": "2026-05-01 12:40 czasu polskiego",
      "remote_filename": "pr3_2025-06-11T04-00-00Z.ogg",
      "station_slug": "pr3",
      "status": "published",
      "utc_label": "2025-06-11 04:00 UTC",
      "utc_started_at": "2025-06-11T04:00:00+00:00",
      "year": 2025
    },
    {
      "archive_item_identifier": "pr3-2025-06-11",
      "audio_url": "https://archive.org/download/pr3-2025-06-11/pr3_2025-06-11T05-00-00Z.ogg",
      "completeness_ratio": 1.0,
      "day": 11,
      "download_url": "https://archive.org/download/pr3-2025-06-11/pr3_2025-06-11T05-00-00Z.ogg",
      "duration_seconds": 3610.019,
      "hour": 7,
      "hourly_archive_id": 33576,
      "local_date_label": "11.06.2025",
      "local_hour_label": "07:00",
      "local_label": "2025-06-11 07:00 czasu polskiego",
      "local_started_at": "2025-06-11T07:00:00+02:00",
      "local_timezone_label": "czasu polskiego",
      "month": 6,
      "published_at": "2026-05-01T10:40:41.430992+00:00",
      "published_local_label": "2026-05-01 12:40 czasu polskiego",
      "remote_filename": "pr3_2025-06-11T05-00-00Z.ogg",
      "station_slug": "pr3",
      "status": "published",
      "utc_label": "2025-06-11 05:00 UTC",
      "utc_started_at": "2025-06-11T05:00:00+00:00",
      "year": 2025
    },
    {
      "archive_item_identifier": "pr3-2025-06-11",
      "audio_url": "https://archive.org/download/pr3-2025-06-11/pr3_2025-06-11T06-00-00Z.ogg",
      "completeness_ratio": 1.0,
      "day": 11,
      "download_url": "https://archive.org/download/pr3-2025-06-11/pr3_2025-06-11T06-00-00Z.ogg",
      "duration_seconds": 3610.012,
      "hour": 8,
      "hourly_archive_id": 33579,
      "local_date_label": "11.06.2025",
      "local_hour_label": "08:00",
      "local_label": "2025-06-11 08:00 czasu polskiego",
      "local_started_at": "2025-06-11T08:00:00+02:00",
      "local_timezone_label": "czasu polskiego",
      "month": 6,
      "published_at": "2026-05-01T10:41:31.712178+00:00",
      "published_local_label": "2026-05-01 12:41 czasu polskiego",
      "remote_filename": "pr3_2025-06-11T06-00-00Z.ogg",
      "station_slug": "pr3",
      "status": "published",
      "utc_label": "2025-06-11 06:00 UTC",
      "utc_started_at": "2025-06-11T06:00:00+00:00",
      "year": 2025
    },
    {
      "archive_item_identifier": "pr3-2025-06-11",
      "audio_url": "https://archive.org/download/pr3-2025-06-11/pr3_2025-06-11T07-00-00Z.ogg",
      "completeness_ratio": 1.0,
      "day": 11,
      "download_url": "https://archive.org/download/pr3-2025-06-11/pr3_2025-06-11T07-00-00Z.ogg",
      "duration_seconds": 3610.001,
      "hour": 9,
      "hourly_archive_id": 33580,
      "local_date_label": "11.06.2025",
      "local_hour_label": "09:00",
      "local_label": "2025-06-11 09:00 czasu polskiego",
      "local_started_at": "2025-06-11T09:00:00+02:00",
      "local_timezone_label": "czasu polskiego",
      "month": 6,
      "published_at": "2026-05-01T10:41:33.980225+00:00",
      "published_local_label": "2026-05-01 12:41 czasu polskiego",
      "remote_filename": "pr3_2025-06-11T07-00-00Z.ogg",
      "station_slug": "pr3",
      "status": "published",
      "utc_label": "2025-06-11 07:00 UTC",
      "utc_started_at": "2025-06-11T07:00:00+00:00",
      "year": 2025
    },
    {
      "archive_item_identifier": "pr3-2025-06-11",
      "audio_url": "https://archive.org/download/pr3-2025-06-11/pr3_2025-06-11T08-00-00Z.ogg",
      "completeness_ratio": 1.0,
      "day": 11,
      "download_url": "https://archive.org/download/pr3-2025-06-11/pr3_2025-06-11T08-00-00Z.ogg",
      "duration_seconds": 3610.016,
      "hour": 10,
      "hourly_archive_id": 33584,
      "local_date_label": "11.06.2025",
      "local_hour_label": "10:00",
      "local_label": "2025-06-11 10:00 czasu polskiego",
      "local_started_at": "2025-06-11T10:00:00+02:00",
      "local_timezone_label": "czasu polskiego",
      "month": 6,
      "published_at": "2026-05-01T10:42:20.660630+00:00",
      "published_local_label": "2026-05-01 12:42 czasu polskiego",
      "remote_filename": "pr3_2025-06-11T08-00-00Z.ogg",
      "station_slug": "pr3",
      "status": "published",
      "utc_label": "2025-06-11 08:00 UTC",
      "utc_started_at": "2025-06-11T08:00:00+00:00",
      "year": 2025
    },
    {
      "archive_item_identifier": "pr3-2025-06-11",
      "audio_url": "https://archive.org/download/pr3-2025-06-11/pr3_2025-06-11T09-00-00Z.ogg",
      "completeness_ratio": 1.0,
      "day": 11,
      "download_url": "https://archive.org/download/pr3-2025-06-11/pr3_2025-06-11T09-00-00Z.ogg",
      "duration_seconds": 3610.001,
      "hour": 11,
      "hourly_archive_id": 33585,
      "local_date_label": "11.06.2025",
      "local_hour_label": "11:00",
      "local_label": "2025-06-11 11:00 czasu polskiego",
      "local_started_at": "2025-06-11T11:00:00+02:00",
      "local_timezone_label": "czasu polskiego",
      "month": 6,
      "published_at": "2026-05-01T10:42:22.903005+00:00",
      "published_local_label": "2026-05-01 12:42 czasu polskiego",
      "remote_filename": "pr3_2025-06-11T09-00-00Z.ogg",
      "station_slug": "pr3",
      "status": "published",
      "utc_label": "2025-06-11 09:00 UTC",
      "utc_started_at": "2025-06-11T09:00:00+00:00",
      "year": 2025
    },
    {
      "archive_item_identifier": "pr3-2025-06-11",
      "audio_url": "https://archive.org/download/pr3-2025-06-11/pr3_2025-06-11T10-00-00Z.ogg",
      "completeness_ratio": 1.0,
      "day": 11,
      "download_url": "https://archive.org/download/pr3-2025-06-11/pr3_2025-06-11T10-00-00Z.ogg",
      "duration_seconds": 3610.008,
      "hour": 12,
      "hourly_archive_id": 33589,
      "local_date_label": "11.06.2025",
      "local_hour_label": "12:00",
      "local_label": "2025-06-11 12:00 czasu polskiego",
      "local_started_at": "2025-06-11T12:00:00+02:00",
      "local_timezone_label": "czasu polskiego",
      "month": 6,
      "published_at": "2026-05-01T10:43:11.107068+00:00",
      "published_local_label": "2026-05-01 12:43 czasu polskiego",
      "remote_filename": "pr3_2025-06-11T10-00-00Z.ogg",
      "station_slug": "pr3",
      "status": "published",
      "utc_label": "2025-06-11 10:00 UTC",
      "utc_started_at": "2025-06-11T10:00:00+00:00",
      "year": 2025
    },
    {
      "archive_item_identifier": "pr3-2025-06-11",
      "audio_url": "https://archive.org/download/pr3-2025-06-11/pr3_2025-06-11T11-00-00Z.ogg",
      "completeness_ratio": 1.0,
      "day": 11,
      "download_url": "https://archive.org/download/pr3-2025-06-11/pr3_2025-06-11T11-00-00Z.ogg",
      "duration_seconds": 3610.008,
      "hour": 13,
      "hourly_archive_id": 33590,
      "local_date_label": "11.06.2025",
      "local_hour_label": "13:00",
      "local_label": "2025-06-11 13:00 czasu polskiego",
      "local_started_at": "2025-06-11T13:00:00+02:00",
      "local_timezone_label": "czasu polskiego",
      "month": 6,
      "published_at": "2026-05-01T10:43:13.324623+00:00",
      "published_local_label": "2026-05-01 12:43 czasu polskiego",
      "remote_filename": "pr3_2025-06-11T11-00-00Z.ogg",
      "station_slug": "pr3",
      "status": "published",
      "utc_label": "2025-06-11 11:00 UTC",
      "utc_started_at": "2025-06-11T11:00:00+00:00",
      "year": 2025
    },
    {
      "archive_item_identifier": "pr3-2025-06-11",
      "audio_url": "https://archive.org/download/pr3-2025-06-11/pr3_2025-06-11T12-00-00Z.ogg",
      "completeness_ratio": 1.0,
      "day": 11,
      "download_url": "https://archive.org/download/pr3-2025-06-11/pr3_2025-06-11T12-00-00Z.ogg",
      "duration_seconds": 3610.013,
      "hour": 14,
      "hourly_archive_id": 33592,
      "local_date_label": "11.06.2025",
      "local_hour_label": "14:00",
      "local_label": "2025-06-11 14:00 czasu polskiego",
      "local_started_at": "2025-06-11T14:00:00+02:00",
      "local_timezone_label": "czasu polskiego",
      "month": 6,
      "published_at": "2026-05-01T10:43:08.996422+00:00",
      "published_local_label": "2026-05-01 12:43 czasu polskiego",
      "remote_filename": "pr3_2025-06-11T12-00-00Z.ogg",
      "station_slug": "pr3",
      "status": "published",
      "utc_label": "2025-06-11 12:00 UTC",
      "utc_started_at": "2025-06-11T12:00:00+00:00",
      "year": 2025
    },
    {
      "archive_item_identifier": "pr3-2025-06-11",
      "audio_url": "https://archive.org/download/pr3-2025-06-11/pr3_2025-06-11T13-00-00Z.ogg",
      "completeness_ratio": 1.0,
      "day": 11,
      "download_url": "https://archive.org/download/pr3-2025-06-11/pr3_2025-06-11T13-00-00Z.ogg",
      "duration_seconds": 3610.001,
      "hour": 15,
      "hourly_archive_id": 33593,
      "local_date_label": "11.06.2025",
      "local_hour_label": "15:00",
      "local_label": "2025-06-11 15:00 czasu polskiego",
      "local_started_at": "2025-06-11T15:00:00+02:00",
      "local_timezone_label": "czasu polskiego",
      "month": 6,
      "published_at": "2026-05-01T10:43:05.282820+00:00",
      "published_local_label": "2026-05-01 12:43 czasu polskiego",
      "remote_filename": "pr3_2025-06-11T13-00-00Z.ogg",
      "station_slug": "pr3",
      "status": "published",
      "utc_label": "2025-06-11 13:00 UTC",
      "utc_started_at": "2025-06-11T13:00:00+00:00",
      "year": 2025
    },
    {
      "archive_item_identifier": "pr3-2025-06-11",
      "audio_url": "https://archive.org/download/pr3-2025-06-11/pr3_2025-06-11T14-00-00Z.ogg",
      "completeness_ratio": 1.0,
      "day": 11,
      "download_url": "https://archive.org/download/pr3-2025-06-11/pr3_2025-06-11T14-00-00Z.ogg",
      "duration_seconds": 3609.991,
      "hour": 16,
      "hourly_archive_id": 33594,
      "local_date_label": "11.06.2025",
      "local_hour_label": "16:00",
      "local_label": "2025-06-11 16:00 czasu polskiego",
      "local_started_at": "2025-06-11T16:00:00+02:00",
      "local_timezone_label": "czasu polskiego",
      "month": 6,
      "published_at": "2026-05-01T10:42:18.489860+00:00",
      "published_local_label": "2026-05-01 12:42 czasu polskiego",
      "remote_filename": "pr3_2025-06-11T14-00-00Z.ogg",
      "station_slug": "pr3",
      "status": "published",
      "utc_label": "2025-06-11 14:00 UTC",
      "utc_started_at": "2025-06-11T14:00:00+00:00",
      "year": 2025
    },
    {
      "archive_item_identifier": "pr3-2025-06-11",
      "audio_url": "https://archive.org/download/pr3-2025-06-11/pr3_2025-06-11T15-00-00Z.ogg",
      "completeness_ratio": 1.0,
      "day": 11,
      "download_url": "https://archive.org/download/pr3-2025-06-11/pr3_2025-06-11T15-00-00Z.ogg",
      "duration_seconds": 3610.003,
      "hour": 17,
      "hourly_archive_id": 33595,
      "local_date_label": "11.06.2025",
      "local_hour_label": "17:00",
      "local_label": "2025-06-11 17:00 czasu polskiego",
      "local_started_at": "2025-06-11T17:00:00+02:00",
      "local_timezone_label": "czasu polskiego",
      "month": 6,
      "published_at": "2026-05-01T10:42:15.481795+00:00",
      "published_local_label": "2026-05-01 12:42 czasu polskiego",
      "remote_filename": "pr3_2025-06-11T15-00-00Z.ogg",
      "station_slug": "pr3",
      "status": "published",
      "utc_label": "2025-06-11 15:00 UTC",
      "utc_started_at": "2025-06-11T15:00:00+00:00",
      "year": 2025
    },
    {
      "archive_item_identifier": "pr3-2025-06-11",
      "audio_url": "https://archive.org/download/pr3-2025-06-11/pr3_2025-06-11T16-00-00Z.ogg",
      "completeness_ratio": 1.0,
      "day": 11,
      "download_url": "https://archive.org/download/pr3-2025-06-11/pr3_2025-06-11T16-00-00Z.ogg",
      "duration_seconds": 3610.005,
      "hour": 18,
      "hourly_archive_id": 33596,
      "local_date_label": "11.06.2025",
      "local_hour_label": "18:00",
      "local_label": "2025-06-11 18:00 czasu polskiego",
      "local_started_at": "2025-06-11T18:00:00+02:00",
      "local_timezone_label": "czasu polskiego",
      "month": 6,
      "published_at": "2026-05-01T10:41:28.196385+00:00",
      "published_local_label": "2026-05-01 12:41 czasu polskiego",
      "remote_filename": "pr3_2025-06-11T16-00-00Z.ogg",
      "station_slug": "pr3",
      "status": "published",
      "utc_label": "2025-06-11 16:00 UTC",
      "utc_started_at": "2025-06-11T16:00:00+00:00",
      "year": 2025
    },
    {
      "archive_item_identifier": "pr3-2025-06-11",
      "audio_url": "https://archive.org/download/pr3-2025-06-11/pr3_2025-06-11T17-00-00Z.ogg",
      "completeness_ratio": 1.0,
      "day": 11,
      "download_url": "https://archive.org/download/pr3-2025-06-11/pr3_2025-06-11T17-00-00Z.ogg",
      "duration_seconds": 3610.013,
      "hour": 19,
      "hourly_archive_id": 33597,
      "local_date_label": "11.06.2025",
      "local_hour_label": "19:00",
      "local_label": "2025-06-11 19:00 czasu polskiego",
      "local_started_at": "2025-06-11T19:00:00+02:00",
      "local_timezone_label": "czasu polskiego",
      "month": 6,
      "published_at": "2026-05-01T10:41:25.730972+00:00",
      "published_local_label": "2026-05-01 12:41 czasu polskiego",
      "remote_filename": "pr3_2025-06-11T17-00-00Z.ogg",
      "station_slug": "pr3",
      "status": "published",
      "utc_label": "2025-06-11 17:00 UTC",
      "utc_started_at": "2025-06-11T17:00:00+00:00",
      "year": 2025
    },
    {
      "archive_item_identifier": "pr3-2025-06-11",
      "audio_url": "https://archive.org/download/pr3-2025-06-11/pr3_2025-06-11T18-00-00Z.ogg",
      "completeness_ratio": 1.0,
      "day": 11,
      "download_url": "https://archive.org/download/pr3-2025-06-11/pr3_2025-06-11T18-00-00Z.ogg",
      "duration_seconds": 3610.001,
      "hour": 20,
      "hourly_archive_id": 33598,
      "local_date_label": "11.06.2025",
      "local_hour_label": "20:00",
      "local_label": "2025-06-11 20:00 czasu polskiego",
      "local_started_at": "2025-06-11T20:00:00+02:00",
      "local_timezone_label": "czasu polskiego",
      "month": 6,
      "published_at": "2026-05-01T10:40:36.798494+00:00",
      "published_local_label": "2026-05-01 12:40 czasu polskiego",
      "remote_filename": "pr3_2025-06-11T18-00-00Z.ogg",
      "station_slug": "pr3",
      "status": "published",
      "utc_label": "2025-06-11 18:00 UTC",
      "utc_started_at": "2025-06-11T18:00:00+00:00",
      "year": 2025
    },
    {
      "archive_item_identifier": "pr3-2025-06-11",
      "audio_url": "https://archive.org/download/pr3-2025-06-11/pr3_2025-06-11T19-00-00Z.ogg",
      "completeness_ratio": 1.0,
      "day": 11,
      "download_url": "https://archive.org/download/pr3-2025-06-11/pr3_2025-06-11T19-00-00Z.ogg",
      "duration_seconds": 3610.016,
      "hour": 21,
      "hourly_archive_id": 33599,
      "local_date_label": "11.06.2025",
      "local_hour_label": "21:00",
      "local_label": "2025-06-11 21:00 czasu polskiego",
      "local_started_at": "2025-06-11T21:00:00+02:00",
      "local_timezone_label": "czasu polskiego",
      "month": 6,
      "published_at": "2026-05-01T10:40:34.519903+00:00",
      "published_local_label": "2026-05-01 12:40 czasu polskiego",
      "remote_filename": "pr3_2025-06-11T19-00-00Z.ogg",
      "station_slug": "pr3",
      "status": "published",
      "utc_label": "2025-06-11 19:00 UTC",
      "utc_started_at": "2025-06-11T19:00:00+00:00",
      "year": 2025
    },
    {
      "archive_item_identifier": "pr3-2025-06-11",
      "audio_url": "https://archive.org/download/pr3-2025-06-11/pr3_2025-06-11T20-00-00Z.ogg",
      "completeness_ratio": 1.0,
      "day": 11,
      "download_url": "https://archive.org/download/pr3-2025-06-11/pr3_2025-06-11T20-00-00Z.ogg",
      "duration_seconds": 3610.008,
      "hour": 22,
      "hourly_archive_id": 33600,
      "local_date_label": "11.06.2025",
      "local_hour_label": "22:00",
      "local_label": "2025-06-11 22:00 czasu polskiego",
      "local_started_at": "2025-06-11T22:00:00+02:00",
      "local_timezone_label": "czasu polskiego",
      "month": 6,
      "published_at": "2026-05-01T10:39:43.541428+00:00",
      "published_local_label": "2026-05-01 12:39 czasu polskiego",
      "remote_filename": "pr3_2025-06-11T20-00-00Z.ogg",
      "station_slug": "pr3",
      "status": "published",
      "utc_label": "2025-06-11 20:00 UTC",
      "utc_started_at": "2025-06-11T20:00:00+00:00",
      "year": 2025
    },
    {
      "archive_item_identifier": "pr3-2025-06-11",
      "audio_url": "https://archive.org/download/pr3-2025-06-11/pr3_2025-06-11T21-00-00Z.ogg",
      "completeness_ratio": 1.0,
      "day": 11,
      "download_url": "https://archive.org/download/pr3-2025-06-11/pr3_2025-06-11T21-00-00Z.ogg",
      "duration_seconds": 3610.011,
      "hour": 23,
      "hourly_archive_id": 33601,
      "local_date_label": "11.06.2025",
      "local_hour_label": "23:00",
      "local_label": "2025-06-11 23:00 czasu polskiego",
      "local_started_at": "2025-06-11T23:00:00+02:00",
      "local_timezone_label": "czasu polskiego",
      "month": 6,
      "published_at": "2026-05-01T10:39:41.039181+00:00",
      "published_local_label": "2026-05-01 12:39 czasu polskiego",
      "remote_filename": "pr3_2025-06-11T21-00-00Z.ogg",
      "station_slug": "pr3",
      "status": "published",
      "utc_label": "2025-06-11 21:00 UTC",
      "utc_started_at": "2025-06-11T21:00:00+00:00",
      "year": 2025
    }
  ],
  "day": 11,
  "generated_at": "2026-05-01T23:02:01.222738+00:00",
  "hour_slots": [
    {
      "archive_status": "published",
      "completeness_ratio": 1.0,
      "day": 11,
      "hour": 0,
      "hourly_archive_id": 33560,
      "local_date_label": "11.06.2025",
      "local_hour_label": "00:00",
      "local_label": "2025-06-11 00:00 czasu polskiego",
      "local_started_at": "2025-06-11T00:00:00+02:00",
      "local_timezone_label": "czasu polskiego",
      "month": 6,
      "playable": true,
      "state": "available",
      "status_label": null,
      "utc_label": "2025-06-10 22:00 UTC",
      "utc_started_at": "2025-06-10T22:00:00+00:00",
      "year": 2025
    },
    {
      "archive_status": "published",
      "completeness_ratio": 1.0,
      "day": 11,
      "hour": 1,
      "hourly_archive_id": 33561,
      "local_date_label": "11.06.2025",
      "local_hour_label": "01:00",
      "local_label": "2025-06-11 01:00 czasu polskiego",
      "local_started_at": "2025-06-11T01:00:00+02:00",
      "local_timezone_label": "czasu polskiego",
      "month": 6,
      "playable": true,
      "state": "available",
      "status_label": null,
      "utc_label": "2025-06-10 23:00 UTC",
      "utc_started_at": "2025-06-10T23:00:00+00:00",
      "year": 2025
    },
    {
      "archive_status": "published",
      "completeness_ratio": 1.0,
      "day": 11,
      "hour": 2,
      "hourly_archive_id": 33565,
      "local_date_label": "11.06.2025",
      "local_hour_label": "02:00",
      "local_label": "2025-06-11 02:00 czasu polskiego",
      "local_started_at": "2025-06-11T02:00:00+02:00",
      "local_timezone_label": "czasu polskiego",
      "month": 6,
      "playable": true,
      "state": "available",
      "status_label": null,
      "utc_label": "2025-06-11 00:00 UTC",
      "utc_started_at": "2025-06-11T00:00:00+00:00",
      "year": 2025
    },
    {
      "archive_status": "published",
      "completeness_ratio": 1.0,
      "day": 11,
      "hour": 3,
      "hourly_archive_id": 33566,
      "local_date_label": "11.06.2025",
      "local_hour_label": "03:00",
      "local_label": "2025-06-11 03:00 czasu polskiego",
      "local_started_at": "2025-06-11T03:00:00+02:00",
      "local_timezone_label": "czasu polskiego",
      "month": 6,
      "playable": true,
      "state": "available",
      "status_label": null,
      "utc_label": "2025-06-11 01:00 UTC",
      "utc_started_at": "2025-06-11T01:00:00+00:00",
      "year": 2025
    },
    {
      "archive_status": "published",
      "completeness_ratio": 1.0,
      "day": 11,
      "hour": 4,
      "hourly_archive_id": 33570,
      "local_date_label": "11.06.2025",
      "local_hour_label": "04:00",
      "local_label": "2025-06-11 04:00 czasu polskiego",
      "local_started_at": "2025-06-11T04:00:00+02:00",
      "local_timezone_label": "czasu polskiego",
      "month": 6,
      "playable": true,
      "state": "available",
      "status_label": null,
      "utc_label": "2025-06-11 02:00 UTC",
      "utc_started_at": "2025-06-11T02:00:00+00:00",
      "year": 2025
    },
    {
      "archive_status": "published",
      "completeness_ratio": 1.0,
      "day": 11,
      "hour": 5,
      "hourly_archive_id": 33571,
      "local_date_label": "11.06.2025",
      "local_hour_label": "05:00",
      "local_label": "2025-06-11 05:00 czasu polskiego",
      "local_started_at": "2025-06-11T05:00:00+02:00",
      "local_timezone_label": "czasu polskiego",
      "month": 6,
      "playable": true,
      "state": "available",
      "status_label": null,
      "utc_label": "2025-06-11 03:00 UTC",
      "utc_started_at": "2025-06-11T03:00:00+00:00",
      "year": 2025
    },
    {
      "archive_status": "published",
      "completeness_ratio": 1.0,
      "day": 11,
      "hour": 6,
      "hourly_archive_id": 33575,
      "local_date_label": "11.06.2025",
      "local_hour_label": "06:00",
      "local_label": "2025-06-11 06:00 czasu polskiego",
      "local_started_at": "2025-06-11T06:00:00+02:00",
      "local_timezone_label": "czasu polskiego",
      "month": 6,
      "playable": true,
      "state": "available",
      "status_label": null,
      "utc_label": "2025-06-11 04:00 UTC",
      "utc_started_at": "2025-06-11T04:00:00+00:00",
      "year": 2025
    },
    {
      "archive_status": "published",
      "completeness_ratio": 1.0,
      "day": 11,
      "hour": 7,
      "hourly_archive_id": 33576,
      "local_date_label": "11.06.2025",
      "local_hour_label": "07:00",
      "local_label": "2025-06-11 07:00 czasu polskiego",
      "local_started_at": "2025-06-11T07:00:00+02:00",
      "local_timezone_label": "czasu polskiego",
      "month": 6,
      "playable": true,
      "state": "available",
      "status_label": null,
      "utc_label": "2025-06-11 05:00 UTC",
      "utc_started_at": "2025-06-11T05:00:00+00:00",
      "year": 2025
    },
    {
      "archive_status": "published",
      "completeness_ratio": 1.0,
      "day": 11,
      "hour": 8,
      "hourly_archive_id": 33579,
      "local_date_label": "11.06.2025",
      "local_hour_label": "08:00",
      "local_label": "2025-06-11 08:00 czasu polskiego",
      "local_started_at": "2025-06-11T08:00:00+02:00",
      "local_timezone_label": "czasu polskiego",
      "month": 6,
      "playable": true,
      "state": "available",
      "status_label": null,
      "utc_label": "2025-06-11 06:00 UTC",
      "utc_started_at": "2025-06-11T06:00:00+00:00",
      "year": 2025
    },
    {
      "archive_status": "published",
      "completeness_ratio": 1.0,
      "day": 11,
      "hour": 9,
      "hourly_archive_id": 33580,
      "local_date_label": "11.06.2025",
      "local_hour_label": "09:00",
      "local_label": "2025-06-11 09:00 czasu polskiego",
      "local_started_at": "2025-06-11T09:00:00+02:00",
      "local_timezone_label": "czasu polskiego",
      "month": 6,
      "playable": true,
      "state": "available",
      "status_label": null,
      "utc_label": "2025-06-11 07:00 UTC",
      "utc_started_at": "2025-06-11T07:00:00+00:00",
      "year": 2025
    },
    {
      "archive_status": "published",
      "completeness_ratio": 1.0,
      "day": 11,
      "hour": 10,
      "hourly_archive_id": 33584,
      "local_date_label": "11.06.2025",
      "local_hour_label": "10:00",
      "local_label": "2025-06-11 10:00 czasu polskiego",
      "local_started_at": "2025-06-11T10:00:00+02:00",
      "local_timezone_label": "czasu polskiego",
      "month": 6,
      "playable": true,
      "state": "available",
      "status_label": null,
      "utc_label": "2025-06-11 08:00 UTC",
      "utc_started_at": "2025-06-11T08:00:00+00:00",
      "year": 2025
    },
    {
      "archive_status": "published",
      "completeness_ratio": 1.0,
      "day": 11,
      "hour": 11,
      "hourly_archive_id": 33585,
      "local_date_label": "11.06.2025",
      "local_hour_label": "11:00",
      "local_label": "2025-06-11 11:00 czasu polskiego",
      "local_started_at": "2025-06-11T11:00:00+02:00",
      "local_timezone_label": "czasu polskiego",
      "month": 6,
      "playable": true,
      "state": "available",
      "status_label": null,
      "utc_label": "2025-06-11 09:00 UTC",
      "utc_started_at": "2025-06-11T09:00:00+00:00",
      "year": 2025
    },
    {
      "archive_status": "published",
      "completeness_ratio": 1.0,
      "day": 11,
      "hour": 12,
      "hourly_archive_id": 33589,
      "local_date_label": "11.06.2025",
      "local_hour_label": "12:00",
      "local_label": "2025-06-11 12:00 czasu polskiego",
      "local_started_at": "2025-06-11T12:00:00+02:00",
      "local_timezone_label": "czasu polskiego",
      "month": 6,
      "playable": true,
      "state": "available",
      "status_label": null,
      "utc_label": "2025-06-11 10:00 UTC",
      "utc_started_at": "2025-06-11T10:00:00+00:00",
      "year": 2025
    },
    {
      "archive_status": "published",
      "completeness_ratio": 1.0,
      "day": 11,
      "hour": 13,
      "hourly_archive_id": 33590,
      "local_date_label": "11.06.2025",
      "local_hour_label": "13:00",
      "local_label": "2025-06-11 13:00 czasu polskiego",
      "local_started_at": "2025-06-11T13:00:00+02:00",
      "local_timezone_label": "czasu polskiego",
      "month": 6,
      "playable": true,
      "state": "available",
      "status_label": null,
      "utc_label": "2025-06-11 11:00 UTC",
      "utc_started_at": "2025-06-11T11:00:00+00:00",
      "year": 2025
    },
    {
      "archive_status": "published",
      "completeness_ratio": 1.0,
      "day": 11,
      "hour": 14,
      "hourly_archive_id": 33592,
      "local_date_label": "11.06.2025",
      "local_hour_label": "14:00",
      "local_label": "2025-06-11 14:00 czasu polskiego",
      "local_started_at": "2025-06-11T14:00:00+02:00",
      "local_timezone_label": "czasu polskiego",
      "month": 6,
      "playable": true,
      "state": "available",
      "status_label": null,
      "utc_label": "2025-06-11 12:00 UTC",
      "utc_started_at": "2025-06-11T12:00:00+00:00",
      "year": 2025
    },
    {
      "archive_status": "published",
      "completeness_ratio": 1.0,
      "day": 11,
      "hour": 15,
      "hourly_archive_id": 33593,
      "local_date_label": "11.06.2025",
      "local_hour_label": "15:00",
      "local_label": "2025-06-11 15:00 czasu polskiego",
      "local_started_at": "2025-06-11T15:00:00+02:00",
      "local_timezone_label": "czasu polskiego",
      "month": 6,
      "playable": true,
      "state": "available",
      "status_label": null,
      "utc_label": "2025-06-11 13:00 UTC",
      "utc_started_at": "2025-06-11T13:00:00+00:00",
      "year": 2025
    },
    {
      "archive_status": "published",
      "completeness_ratio": 1.0,
      "day": 11,
      "hour": 16,
      "hourly_archive_id": 33594,
      "local_date_label": "11.06.2025",
      "local_hour_label": "16:00",
      "local_label": "2025-06-11 16:00 czasu polskiego",
      "local_started_at": "2025-06-11T16:00:00+02:00",
      "local_timezone_label": "czasu polskiego",
      "month": 6,
      "playable": true,
      "state": "available",
      "status_label": null,
      "utc_label": "2025-06-11 14:00 UTC",
      "utc_started_at": "2025-06-11T14:00:00+00:00",
      "year": 2025
    },
    {
      "archive_status": "published",
      "completeness_ratio": 1.0,
      "day": 11,
      "hour": 17,
      "hourly_archive_id": 33595,
      "local_date_label": "11.06.2025",
      "local_hour_label": "17:00",
      "local_label": "2025-06-11 17:00 czasu polskiego",
      "local_started_at": "2025-06-11T17:00:00+02:00",
      "local_timezone_label": "czasu polskiego",
      "month": 6,
      "playable": true,
      "state": "available",
      "status_label": null,
      "utc_label": "2025-06-11 15:00 UTC",
      "utc_started_at": "2025-06-11T15:00:00+00:00",
      "year": 2025
    },
    {
      "archive_status": "published",
      "completeness_ratio": 1.0,
      "day": 11,
      "hour": 18,
      "hourly_archive_id": 33596,
      "local_date_label": "11.06.2025",
      "local_hour_label": "18:00",
      "local_label": "2025-06-11 18:00 czasu polskiego",
      "local_started_at": "2025-06-11T18:00:00+02:00",
      "local_timezone_label": "czasu polskiego",
      "month": 6,
      "playable": true,
      "state": "available",
      "status_label": null,
      "utc_label": "2025-06-11 16:00 UTC",
      "utc_started_at": "2025-06-11T16:00:00+00:00",
      "year": 2025
    },
    {
      "archive_status": "published",
      "completeness_ratio": 1.0,
      "day": 11,
      "hour": 19,
      "hourly_archive_id": 33597,
      "local_date_label": "11.06.2025",
      "local_hour_label": "19:00",
      "local_label": "2025-06-11 19:00 czasu polskiego",
      "local_started_at": "2025-06-11T19:00:00+02:00",
      "local_timezone_label": "czasu polskiego",
      "month": 6,
      "playable": true,
      "state": "available",
      "status_label": null,
      "utc_label": "2025-06-11 17:00 UTC",
      "utc_started_at": "2025-06-11T17:00:00+00:00",
      "year": 2025
    },
    {
      "archive_status": "published",
      "completeness_ratio": 1.0,
      "day": 11,
      "hour": 20,
      "hourly_archive_id": 33598,
      "local_date_label": "11.06.2025",
      "local_hour_label": "20:00",
      "local_label": "2025-06-11 20:00 czasu polskiego",
      "local_started_at": "2025-06-11T20:00:00+02:00",
      "local_timezone_label": "czasu polskiego",
      "month": 6,
      "playable": true,
      "state": "available",
      "status_label": null,
      "utc_label": "2025-06-11 18:00 UTC",
      "utc_started_at": "2025-06-11T18:00:00+00:00",
      "year": 2025
    },
    {
      "archive_status": "published",
      "completeness_ratio": 1.0,
      "day": 11,
      "hour": 21,
      "hourly_archive_id": 33599,
      "local_date_label": "11.06.2025",
      "local_hour_label": "21:00",
      "local_label": "2025-06-11 21:00 czasu polskiego",
      "local_started_at": "2025-06-11T21:00:00+02:00",
      "local_timezone_label": "czasu polskiego",
      "month": 6,
      "playable": true,
      "state": "available",
      "status_label": null,
      "utc_label": "2025-06-11 19:00 UTC",
      "utc_started_at": "2025-06-11T19:00:00+00:00",
      "year": 2025
    },
    {
      "archive_status": "published",
      "completeness_ratio": 1.0,
      "day": 11,
      "hour": 22,
      "hourly_archive_id": 33600,
      "local_date_label": "11.06.2025",
      "local_hour_label": "22:00",
      "local_label": "2025-06-11 22:00 czasu polskiego",
      "local_started_at": "2025-06-11T22:00:00+02:00",
      "local_timezone_label": "czasu polskiego",
      "month": 6,
      "playable": true,
      "state": "available",
      "status_label": null,
      "utc_label": "2025-06-11 20:00 UTC",
      "utc_started_at": "2025-06-11T20:00:00+00:00",
      "year": 2025
    },
    {
      "archive_status": "published",
      "completeness_ratio": 1.0,
      "day": 11,
      "hour": 23,
      "hourly_archive_id": 33601,
      "local_date_label": "11.06.2025",
      "local_hour_label": "23:00",
      "local_label": "2025-06-11 23:00 czasu polskiego",
      "local_started_at": "2025-06-11T23:00:00+02:00",
      "local_timezone_label": "czasu polskiego",
      "month": 6,
      "playable": true,
      "state": "available",
      "status_label": null,
      "utc_label": "2025-06-11 21:00 UTC",
      "utc_started_at": "2025-06-11T21:00:00+00:00",
      "year": 2025
    }
  ],
  "latest_archive_hour_expected_station_count": 0,
  "latest_archive_hour_started_at": "2026-05-01T21:00:00+00:00",
  "month": 6,
  "published_at": "2026-05-01T23:02:01.222738+00:00",
  "station": {
    "archive_count": 7834,
    "display_name": "Program 3",
    "public_name": "Polskie Radio Program 3",
    "slug": "pr3",
    "timezone": "Europe/Warsaw"
  },
  "year": 2025
}
