{
  "archives": [
    {
      "archive_item_identifier": "pr3-2026-01-02",
      "audio_url": "https://archive.org/download/pr3-2026-01-02/pr3_2026-01-02T23-00-00Z.ogg",
      "completeness_ratio": 1.0,
      "day": 3,
      "download_url": "https://archive.org/download/pr3-2026-01-02/pr3_2026-01-02T23-00-00Z.ogg",
      "duration_seconds": 3610.019,
      "hour": 0,
      "hourly_archive_id": 17582,
      "local_date_label": "03.01.2026",
      "local_hour_label": "00:00",
      "local_label": "2026-01-03 00:00 czasu polskiego",
      "local_started_at": "2026-01-03T00:00:00+01:00",
      "local_timezone_label": "czasu polskiego",
      "month": 1,
      "published_at": "2026-04-17T04:47:46.270990+00:00",
      "published_local_label": "2026-04-17 06:47 czasu polskiego",
      "remote_filename": "pr3_2026-01-02T23-00-00Z.ogg",
      "station_slug": "pr3",
      "status": "published",
      "utc_label": "2026-01-02 23:00 UTC",
      "utc_started_at": "2026-01-02T23:00:00+00:00",
      "year": 2026
    },
    {
      "archive_item_identifier": "pr3-2026-01-03",
      "audio_url": "https://archive.org/download/pr3-2026-01-03/pr3_2026-01-03T00-00-00Z.ogg",
      "completeness_ratio": 1.0,
      "day": 3,
      "download_url": "https://archive.org/download/pr3-2026-01-03/pr3_2026-01-03T00-00-00Z.ogg",
      "duration_seconds": 3610.003,
      "hour": 1,
      "hourly_archive_id": 17584,
      "local_date_label": "03.01.2026",
      "local_hour_label": "01:00",
      "local_label": "2026-01-03 01:00 czasu polskiego",
      "local_started_at": "2026-01-03T01:00:00+01:00",
      "local_timezone_label": "czasu polskiego",
      "month": 1,
      "published_at": "2026-04-17T04:47:51.665459+00:00",
      "published_local_label": "2026-04-17 06:47 czasu polskiego",
      "remote_filename": "pr3_2026-01-03T00-00-00Z.ogg",
      "station_slug": "pr3",
      "status": "published",
      "utc_label": "2026-01-03 00:00 UTC",
      "utc_started_at": "2026-01-03T00:00:00+00:00",
      "year": 2026
    },
    {
      "archive_item_identifier": "pr3-2026-01-03",
      "audio_url": "https://archive.org/download/pr3-2026-01-03/pr3_2026-01-03T01-00-00Z.ogg",
      "completeness_ratio": 1.0,
      "day": 3,
      "download_url": "https://archive.org/download/pr3-2026-01-03/pr3_2026-01-03T01-00-00Z.ogg",
      "duration_seconds": 3610.011,
      "hour": 2,
      "hourly_archive_id": 17593,
      "local_date_label": "03.01.2026",
      "local_hour_label": "02:00",
      "local_label": "2026-01-03 02:00 czasu polskiego",
      "local_started_at": "2026-01-03T02:00:00+01:00",
      "local_timezone_label": "czasu polskiego",
      "month": 1,
      "published_at": "2026-04-17T04:47:54.169203+00:00",
      "published_local_label": "2026-04-17 06:47 czasu polskiego",
      "remote_filename": "pr3_2026-01-03T01-00-00Z.ogg",
      "station_slug": "pr3",
      "status": "published",
      "utc_label": "2026-01-03 01:00 UTC",
      "utc_started_at": "2026-01-03T01:00:00+00:00",
      "year": 2026
    },
    {
      "archive_item_identifier": "pr3-2026-01-03",
      "audio_url": "https://archive.org/download/pr3-2026-01-03/pr3_2026-01-03T02-00-00Z.ogg",
      "completeness_ratio": 1.0,
      "day": 3,
      "download_url": "https://archive.org/download/pr3-2026-01-03/pr3_2026-01-03T02-00-00Z.ogg",
      "duration_seconds": 3609.992,
      "hour": 3,
      "hourly_archive_id": 17594,
      "local_date_label": "03.01.2026",
      "local_hour_label": "03:00",
      "local_label": "2026-01-03 03:00 czasu polskiego",
      "local_started_at": "2026-01-03T03:00:00+01:00",
      "local_timezone_label": "czasu polskiego",
      "month": 1,
      "published_at": "2026-04-17T04:47:56.427737+00:00",
      "published_local_label": "2026-04-17 06:47 czasu polskiego",
      "remote_filename": "pr3_2026-01-03T02-00-00Z.ogg",
      "station_slug": "pr3",
      "status": "published",
      "utc_label": "2026-01-03 02:00 UTC",
      "utc_started_at": "2026-01-03T02:00:00+00:00",
      "year": 2026
    },
    {
      "archive_item_identifier": "pr3-2026-01-03",
      "audio_url": "https://archive.org/download/pr3-2026-01-03/pr3_2026-01-03T03-00-00Z.ogg",
      "completeness_ratio": 1.0,
      "day": 3,
      "download_url": "https://archive.org/download/pr3-2026-01-03/pr3_2026-01-03T03-00-00Z.ogg",
      "duration_seconds": 3610.001,
      "hour": 4,
      "hourly_archive_id": 17595,
      "local_date_label": "03.01.2026",
      "local_hour_label": "04:00",
      "local_label": "2026-01-03 04:00 czasu polskiego",
      "local_started_at": "2026-01-03T04:00:00+01:00",
      "local_timezone_label": "czasu polskiego",
      "month": 1,
      "published_at": "2026-04-17T04:48:07.182733+00:00",
      "published_local_label": "2026-04-17 06:48 czasu polskiego",
      "remote_filename": "pr3_2026-01-03T03-00-00Z.ogg",
      "station_slug": "pr3",
      "status": "published",
      "utc_label": "2026-01-03 03:00 UTC",
      "utc_started_at": "2026-01-03T03:00:00+00:00",
      "year": 2026
    },
    {
      "archive_item_identifier": "pr3-2026-01-03",
      "audio_url": "https://archive.org/download/pr3-2026-01-03/pr3_2026-01-03T04-00-00Z.ogg",
      "completeness_ratio": 1.0,
      "day": 3,
      "download_url": "https://archive.org/download/pr3-2026-01-03/pr3_2026-01-03T04-00-00Z.ogg",
      "duration_seconds": 3610.001,
      "hour": 5,
      "hourly_archive_id": 17596,
      "local_date_label": "03.01.2026",
      "local_hour_label": "05:00",
      "local_label": "2026-01-03 05:00 czasu polskiego",
      "local_started_at": "2026-01-03T05:00:00+01:00",
      "local_timezone_label": "czasu polskiego",
      "month": 1,
      "published_at": "2026-04-17T04:48:10.709022+00:00",
      "published_local_label": "2026-04-17 06:48 czasu polskiego",
      "remote_filename": "pr3_2026-01-03T04-00-00Z.ogg",
      "station_slug": "pr3",
      "status": "published",
      "utc_label": "2026-01-03 04:00 UTC",
      "utc_started_at": "2026-01-03T04:00:00+00:00",
      "year": 2026
    },
    {
      "archive_item_identifier": "pr3-2026-01-03",
      "audio_url": "https://archive.org/download/pr3-2026-01-03/pr3_2026-01-03T05-00-00Z.ogg",
      "completeness_ratio": 1.0,
      "day": 3,
      "download_url": "https://archive.org/download/pr3-2026-01-03/pr3_2026-01-03T05-00-00Z.ogg",
      "duration_seconds": 3610.007,
      "hour": 6,
      "hourly_archive_id": 17597,
      "local_date_label": "03.01.2026",
      "local_hour_label": "06:00",
      "local_label": "2026-01-03 06:00 czasu polskiego",
      "local_started_at": "2026-01-03T06:00:00+01:00",
      "local_timezone_label": "czasu polskiego",
      "month": 1,
      "published_at": "2026-04-17T04:48:20.266400+00:00",
      "published_local_label": "2026-04-17 06:48 czasu polskiego",
      "remote_filename": "pr3_2026-01-03T05-00-00Z.ogg",
      "station_slug": "pr3",
      "status": "published",
      "utc_label": "2026-01-03 05:00 UTC",
      "utc_started_at": "2026-01-03T05:00:00+00:00",
      "year": 2026
    },
    {
      "archive_item_identifier": "pr3-2026-01-03",
      "audio_url": "https://archive.org/download/pr3-2026-01-03/pr3_2026-01-03T06-00-00Z.ogg",
      "completeness_ratio": 1.0,
      "day": 3,
      "download_url": "https://archive.org/download/pr3-2026-01-03/pr3_2026-01-03T06-00-00Z.ogg",
      "duration_seconds": 3610.001,
      "hour": 7,
      "hourly_archive_id": 17598,
      "local_date_label": "03.01.2026",
      "local_hour_label": "07:00",
      "local_label": "2026-01-03 07:00 czasu polskiego",
      "local_started_at": "2026-01-03T07:00:00+01:00",
      "local_timezone_label": "czasu polskiego",
      "month": 1,
      "published_at": "2026-04-17T04:48:23.971519+00:00",
      "published_local_label": "2026-04-17 06:48 czasu polskiego",
      "remote_filename": "pr3_2026-01-03T06-00-00Z.ogg",
      "station_slug": "pr3",
      "status": "published",
      "utc_label": "2026-01-03 06:00 UTC",
      "utc_started_at": "2026-01-03T06:00:00+00:00",
      "year": 2026
    },
    {
      "archive_item_identifier": "pr3-2026-01-03",
      "audio_url": "https://archive.org/download/pr3-2026-01-03/pr3_2026-01-03T07-00-00Z.ogg",
      "completeness_ratio": 1.0,
      "day": 3,
      "download_url": "https://archive.org/download/pr3-2026-01-03/pr3_2026-01-03T07-00-00Z.ogg",
      "duration_seconds": 3610.013,
      "hour": 8,
      "hourly_archive_id": 17599,
      "local_date_label": "03.01.2026",
      "local_hour_label": "08:00",
      "local_label": "2026-01-03 08:00 czasu polskiego",
      "local_started_at": "2026-01-03T08:00:00+01:00",
      "local_timezone_label": "czasu polskiego",
      "month": 1,
      "published_at": "2026-04-17T04:48:26.382642+00:00",
      "published_local_label": "2026-04-17 06:48 czasu polskiego",
      "remote_filename": "pr3_2026-01-03T07-00-00Z.ogg",
      "station_slug": "pr3",
      "status": "published",
      "utc_label": "2026-01-03 07:00 UTC",
      "utc_started_at": "2026-01-03T07:00:00+00:00",
      "year": 2026
    },
    {
      "archive_item_identifier": "pr3-2026-01-03",
      "audio_url": "https://archive.org/download/pr3-2026-01-03/pr3_2026-01-03T08-00-00Z.ogg",
      "completeness_ratio": 1.0,
      "day": 3,
      "download_url": "https://archive.org/download/pr3-2026-01-03/pr3_2026-01-03T08-00-00Z.ogg",
      "duration_seconds": 3610.013,
      "hour": 9,
      "hourly_archive_id": 17600,
      "local_date_label": "03.01.2026",
      "local_hour_label": "09:00",
      "local_label": "2026-01-03 09:00 czasu polskiego",
      "local_started_at": "2026-01-03T09:00:00+01:00",
      "local_timezone_label": "czasu polskiego",
      "month": 1,
      "published_at": "2026-04-17T04:48:28.916751+00:00",
      "published_local_label": "2026-04-17 06:48 czasu polskiego",
      "remote_filename": "pr3_2026-01-03T08-00-00Z.ogg",
      "station_slug": "pr3",
      "status": "published",
      "utc_label": "2026-01-03 08:00 UTC",
      "utc_started_at": "2026-01-03T08:00:00+00:00",
      "year": 2026
    },
    {
      "archive_item_identifier": "pr3-2026-01-03",
      "audio_url": "https://archive.org/download/pr3-2026-01-03/pr3_2026-01-03T09-00-00Z.ogg",
      "completeness_ratio": 1.0,
      "day": 3,
      "download_url": "https://archive.org/download/pr3-2026-01-03/pr3_2026-01-03T09-00-00Z.ogg",
      "duration_seconds": 3610.012,
      "hour": 10,
      "hourly_archive_id": 17601,
      "local_date_label": "03.01.2026",
      "local_hour_label": "10:00",
      "local_label": "2026-01-03 10:00 czasu polskiego",
      "local_started_at": "2026-01-03T10:00:00+01:00",
      "local_timezone_label": "czasu polskiego",
      "month": 1,
      "published_at": "2026-04-17T04:48:31.449625+00:00",
      "published_local_label": "2026-04-17 06:48 czasu polskiego",
      "remote_filename": "pr3_2026-01-03T09-00-00Z.ogg",
      "station_slug": "pr3",
      "status": "published",
      "utc_label": "2026-01-03 09:00 UTC",
      "utc_started_at": "2026-01-03T09:00:00+00:00",
      "year": 2026
    },
    {
      "archive_item_identifier": "pr3-2026-01-03",
      "audio_url": "https://archive.org/download/pr3-2026-01-03/pr3_2026-01-03T10-00-00Z.ogg",
      "completeness_ratio": 1.0,
      "day": 3,
      "download_url": "https://archive.org/download/pr3-2026-01-03/pr3_2026-01-03T10-00-00Z.ogg",
      "duration_seconds": 3610.007,
      "hour": 11,
      "hourly_archive_id": 17602,
      "local_date_label": "03.01.2026",
      "local_hour_label": "11:00",
      "local_label": "2026-01-03 11:00 czasu polskiego",
      "local_started_at": "2026-01-03T11:00:00+01:00",
      "local_timezone_label": "czasu polskiego",
      "month": 1,
      "published_at": "2026-04-17T04:48:34.937593+00:00",
      "published_local_label": "2026-04-17 06:48 czasu polskiego",
      "remote_filename": "pr3_2026-01-03T10-00-00Z.ogg",
      "station_slug": "pr3",
      "status": "published",
      "utc_label": "2026-01-03 10:00 UTC",
      "utc_started_at": "2026-01-03T10:00:00+00:00",
      "year": 2026
    },
    {
      "archive_item_identifier": "pr3-2026-01-03",
      "audio_url": "https://archive.org/download/pr3-2026-01-03/pr3_2026-01-03T11-00-00Z.ogg",
      "completeness_ratio": 1.0,
      "day": 3,
      "download_url": "https://archive.org/download/pr3-2026-01-03/pr3_2026-01-03T11-00-00Z.ogg",
      "duration_seconds": 3610.004,
      "hour": 12,
      "hourly_archive_id": 17603,
      "local_date_label": "03.01.2026",
      "local_hour_label": "12:00",
      "local_label": "2026-01-03 12:00 czasu polskiego",
      "local_started_at": "2026-01-03T12:00:00+01:00",
      "local_timezone_label": "czasu polskiego",
      "month": 1,
      "published_at": "2026-04-17T04:48:37.202830+00:00",
      "published_local_label": "2026-04-17 06:48 czasu polskiego",
      "remote_filename": "pr3_2026-01-03T11-00-00Z.ogg",
      "station_slug": "pr3",
      "status": "published",
      "utc_label": "2026-01-03 11:00 UTC",
      "utc_started_at": "2026-01-03T11:00:00+00:00",
      "year": 2026
    },
    {
      "archive_item_identifier": "pr3-2026-01-03",
      "audio_url": "https://archive.org/download/pr3-2026-01-03/pr3_2026-01-03T12-00-00Z.ogg",
      "completeness_ratio": 1.0,
      "day": 3,
      "download_url": "https://archive.org/download/pr3-2026-01-03/pr3_2026-01-03T12-00-00Z.ogg",
      "duration_seconds": 3610.001,
      "hour": 13,
      "hourly_archive_id": 17604,
      "local_date_label": "03.01.2026",
      "local_hour_label": "13:00",
      "local_label": "2026-01-03 13:00 czasu polskiego",
      "local_started_at": "2026-01-03T13:00:00+01:00",
      "local_timezone_label": "czasu polskiego",
      "month": 1,
      "published_at": "2026-04-17T04:50:43.799888+00:00",
      "published_local_label": "2026-04-17 06:50 czasu polskiego",
      "remote_filename": "pr3_2026-01-03T12-00-00Z.ogg",
      "station_slug": "pr3",
      "status": "published",
      "utc_label": "2026-01-03 12:00 UTC",
      "utc_started_at": "2026-01-03T12:00:00+00:00",
      "year": 2026
    },
    {
      "archive_item_identifier": "pr3-2026-01-03",
      "audio_url": "https://archive.org/download/pr3-2026-01-03/pr3_2026-01-03T13-00-00Z.ogg",
      "completeness_ratio": 1.0,
      "day": 3,
      "download_url": "https://archive.org/download/pr3-2026-01-03/pr3_2026-01-03T13-00-00Z.ogg",
      "duration_seconds": 3610.009,
      "hour": 14,
      "hourly_archive_id": 17605,
      "local_date_label": "03.01.2026",
      "local_hour_label": "14:00",
      "local_label": "2026-01-03 14:00 czasu polskiego",
      "local_started_at": "2026-01-03T14:00:00+01:00",
      "local_timezone_label": "czasu polskiego",
      "month": 1,
      "published_at": "2026-04-17T04:50:48.700185+00:00",
      "published_local_label": "2026-04-17 06:50 czasu polskiego",
      "remote_filename": "pr3_2026-01-03T13-00-00Z.ogg",
      "station_slug": "pr3",
      "status": "published",
      "utc_label": "2026-01-03 13:00 UTC",
      "utc_started_at": "2026-01-03T13:00:00+00:00",
      "year": 2026
    },
    {
      "archive_item_identifier": "pr3-2026-01-03",
      "audio_url": "https://archive.org/download/pr3-2026-01-03/pr3_2026-01-03T14-00-00Z.ogg",
      "completeness_ratio": 1.0,
      "day": 3,
      "download_url": "https://archive.org/download/pr3-2026-01-03/pr3_2026-01-03T14-00-00Z.ogg",
      "duration_seconds": 3610.0,
      "hour": 15,
      "hourly_archive_id": 17606,
      "local_date_label": "03.01.2026",
      "local_hour_label": "15:00",
      "local_label": "2026-01-03 15:00 czasu polskiego",
      "local_started_at": "2026-01-03T15:00:00+01:00",
      "local_timezone_label": "czasu polskiego",
      "month": 1,
      "published_at": "2026-04-17T04:50:50.954736+00:00",
      "published_local_label": "2026-04-17 06:50 czasu polskiego",
      "remote_filename": "pr3_2026-01-03T14-00-00Z.ogg",
      "station_slug": "pr3",
      "status": "published",
      "utc_label": "2026-01-03 14:00 UTC",
      "utc_started_at": "2026-01-03T14:00:00+00:00",
      "year": 2026
    },
    {
      "archive_item_identifier": "pr3-2026-01-03",
      "audio_url": "https://archive.org/download/pr3-2026-01-03/pr3_2026-01-03T15-00-00Z.ogg",
      "completeness_ratio": 1.0,
      "day": 3,
      "download_url": "https://archive.org/download/pr3-2026-01-03/pr3_2026-01-03T15-00-00Z.ogg",
      "duration_seconds": 3610.013,
      "hour": 16,
      "hourly_archive_id": 17607,
      "local_date_label": "03.01.2026",
      "local_hour_label": "16:00",
      "local_label": "2026-01-03 16:00 czasu polskiego",
      "local_started_at": "2026-01-03T16:00:00+01:00",
      "local_timezone_label": "czasu polskiego",
      "month": 1,
      "published_at": "2026-04-17T04:50:53.105419+00:00",
      "published_local_label": "2026-04-17 06:50 czasu polskiego",
      "remote_filename": "pr3_2026-01-03T15-00-00Z.ogg",
      "station_slug": "pr3",
      "status": "published",
      "utc_label": "2026-01-03 15:00 UTC",
      "utc_started_at": "2026-01-03T15:00:00+00:00",
      "year": 2026
    },
    {
      "archive_item_identifier": "pr3-2026-01-03",
      "audio_url": "https://archive.org/download/pr3-2026-01-03/pr3_2026-01-03T16-00-00Z.ogg",
      "completeness_ratio": 1.0,
      "day": 3,
      "download_url": "https://archive.org/download/pr3-2026-01-03/pr3_2026-01-03T16-00-00Z.ogg",
      "duration_seconds": 3610.003,
      "hour": 17,
      "hourly_archive_id": 17608,
      "local_date_label": "03.01.2026",
      "local_hour_label": "17:00",
      "local_label": "2026-01-03 17:00 czasu polskiego",
      "local_started_at": "2026-01-03T17:00:00+01:00",
      "local_timezone_label": "czasu polskiego",
      "month": 1,
      "published_at": "2026-04-17T04:50:55.154412+00:00",
      "published_local_label": "2026-04-17 06:50 czasu polskiego",
      "remote_filename": "pr3_2026-01-03T16-00-00Z.ogg",
      "station_slug": "pr3",
      "status": "published",
      "utc_label": "2026-01-03 16:00 UTC",
      "utc_started_at": "2026-01-03T16:00:00+00:00",
      "year": 2026
    },
    {
      "archive_item_identifier": "pr3-2026-01-03",
      "audio_url": "https://archive.org/download/pr3-2026-01-03/pr3_2026-01-03T17-00-00Z.ogg",
      "completeness_ratio": 1.0,
      "day": 3,
      "download_url": "https://archive.org/download/pr3-2026-01-03/pr3_2026-01-03T17-00-00Z.ogg",
      "duration_seconds": 3610.001,
      "hour": 18,
      "hourly_archive_id": 17609,
      "local_date_label": "03.01.2026",
      "local_hour_label": "18:00",
      "local_label": "2026-01-03 18:00 czasu polskiego",
      "local_started_at": "2026-01-03T18:00:00+01:00",
      "local_timezone_label": "czasu polskiego",
      "month": 1,
      "published_at": "2026-04-17T04:50:57.970361+00:00",
      "published_local_label": "2026-04-17 06:50 czasu polskiego",
      "remote_filename": "pr3_2026-01-03T17-00-00Z.ogg",
      "station_slug": "pr3",
      "status": "published",
      "utc_label": "2026-01-03 17:00 UTC",
      "utc_started_at": "2026-01-03T17:00:00+00:00",
      "year": 2026
    },
    {
      "archive_item_identifier": "pr3-2026-01-03",
      "audio_url": "https://archive.org/download/pr3-2026-01-03/pr3_2026-01-03T18-00-00Z.ogg",
      "completeness_ratio": 1.0,
      "day": 3,
      "download_url": "https://archive.org/download/pr3-2026-01-03/pr3_2026-01-03T18-00-00Z.ogg",
      "duration_seconds": 3610.016,
      "hour": 19,
      "hourly_archive_id": 17610,
      "local_date_label": "03.01.2026",
      "local_hour_label": "19:00",
      "local_label": "2026-01-03 19:00 czasu polskiego",
      "local_started_at": "2026-01-03T19:00:00+01:00",
      "local_timezone_label": "czasu polskiego",
      "month": 1,
      "published_at": "2026-04-17T04:51:00.227728+00:00",
      "published_local_label": "2026-04-17 06:51 czasu polskiego",
      "remote_filename": "pr3_2026-01-03T18-00-00Z.ogg",
      "station_slug": "pr3",
      "status": "published",
      "utc_label": "2026-01-03 18:00 UTC",
      "utc_started_at": "2026-01-03T18:00:00+00:00",
      "year": 2026
    },
    {
      "archive_item_identifier": "pr3-2026-01-03",
      "audio_url": "https://archive.org/download/pr3-2026-01-03/pr3_2026-01-03T19-00-00Z.ogg",
      "completeness_ratio": 1.0,
      "day": 3,
      "download_url": "https://archive.org/download/pr3-2026-01-03/pr3_2026-01-03T19-00-00Z.ogg",
      "duration_seconds": 3610.008,
      "hour": 20,
      "hourly_archive_id": 17611,
      "local_date_label": "03.01.2026",
      "local_hour_label": "20:00",
      "local_label": "2026-01-03 20:00 czasu polskiego",
      "local_started_at": "2026-01-03T20:00:00+01:00",
      "local_timezone_label": "czasu polskiego",
      "month": 1,
      "published_at": "2026-04-17T04:51:02.490237+00:00",
      "published_local_label": "2026-04-17 06:51 czasu polskiego",
      "remote_filename": "pr3_2026-01-03T19-00-00Z.ogg",
      "station_slug": "pr3",
      "status": "published",
      "utc_label": "2026-01-03 19:00 UTC",
      "utc_started_at": "2026-01-03T19:00:00+00:00",
      "year": 2026
    },
    {
      "archive_item_identifier": "pr3-2026-01-03",
      "audio_url": "https://archive.org/download/pr3-2026-01-03/pr3_2026-01-03T20-00-00Z.ogg",
      "completeness_ratio": 0.208,
      "day": 3,
      "download_url": "https://archive.org/download/pr3-2026-01-03/pr3_2026-01-03T20-00-00Z.ogg",
      "duration_seconds": 748.891,
      "hour": 21,
      "hourly_archive_id": 17612,
      "local_date_label": "03.01.2026",
      "local_hour_label": "21:00",
      "local_label": "2026-01-03 21:00 czasu polskiego",
      "local_started_at": "2026-01-03T21:00:00+01:00",
      "local_timezone_label": "czasu polskiego",
      "month": 1,
      "published_at": "2026-04-17T04:51:14.755463+00:00",
      "published_local_label": "2026-04-17 06:51 czasu polskiego",
      "remote_filename": "pr3_2026-01-03T20-00-00Z.ogg",
      "station_slug": "pr3",
      "status": "published",
      "utc_label": "2026-01-03 20:00 UTC",
      "utc_started_at": "2026-01-03T20:00:00+00:00",
      "year": 2026
    },
    {
      "archive_item_identifier": "pr3-2026-01-03",
      "audio_url": "https://archive.org/download/pr3-2026-01-03/pr3_2026-01-03T21-00-00Z.ogg",
      "completeness_ratio": 1.0,
      "day": 3,
      "download_url": "https://archive.org/download/pr3-2026-01-03/pr3_2026-01-03T21-00-00Z.ogg",
      "duration_seconds": 3610.001,
      "hour": 22,
      "hourly_archive_id": 17613,
      "local_date_label": "03.01.2026",
      "local_hour_label": "22:00",
      "local_label": "2026-01-03 22:00 czasu polskiego",
      "local_started_at": "2026-01-03T22:00:00+01:00",
      "local_timezone_label": "czasu polskiego",
      "month": 1,
      "published_at": "2026-04-17T04:51:04.795260+00:00",
      "published_local_label": "2026-04-17 06:51 czasu polskiego",
      "remote_filename": "pr3_2026-01-03T21-00-00Z.ogg",
      "station_slug": "pr3",
      "status": "published",
      "utc_label": "2026-01-03 21:00 UTC",
      "utc_started_at": "2026-01-03T21:00:00+00:00",
      "year": 2026
    },
    {
      "archive_item_identifier": "pr3-2026-01-03",
      "audio_url": "https://archive.org/download/pr3-2026-01-03/pr3_2026-01-03T22-00-00Z.ogg",
      "completeness_ratio": 1.0,
      "day": 3,
      "download_url": "https://archive.org/download/pr3-2026-01-03/pr3_2026-01-03T22-00-00Z.ogg",
      "duration_seconds": 3610.009,
      "hour": 23,
      "hourly_archive_id": 17614,
      "local_date_label": "03.01.2026",
      "local_hour_label": "23:00",
      "local_label": "2026-01-03 23:00 czasu polskiego",
      "local_started_at": "2026-01-03T23:00:00+01:00",
      "local_timezone_label": "czasu polskiego",
      "month": 1,
      "published_at": "2026-04-17T04:48:04.818314+00:00",
      "published_local_label": "2026-04-17 06:48 czasu polskiego",
      "remote_filename": "pr3_2026-01-03T22-00-00Z.ogg",
      "station_slug": "pr3",
      "status": "published",
      "utc_label": "2026-01-03 22:00 UTC",
      "utc_started_at": "2026-01-03T22:00:00+00:00",
      "year": 2026
    }
  ],
  "day": 3,
  "generated_at": "2026-04-25T19:53:05.580680+00:00",
  "hour_slots": [
    {
      "archive_status": "published",
      "completeness_ratio": 1.0,
      "day": 3,
      "hour": 0,
      "hourly_archive_id": 17582,
      "local_date_label": "03.01.2026",
      "local_hour_label": "00:00",
      "local_label": "2026-01-03 00:00 czasu polskiego",
      "local_started_at": "2026-01-03T00:00:00+01:00",
      "local_timezone_label": "czasu polskiego",
      "month": 1,
      "playable": true,
      "state": "available",
      "status_label": null,
      "utc_label": "2026-01-02 23:00 UTC",
      "utc_started_at": "2026-01-02T23:00:00+00:00",
      "year": 2026
    },
    {
      "archive_status": "published",
      "completeness_ratio": 1.0,
      "day": 3,
      "hour": 1,
      "hourly_archive_id": 17584,
      "local_date_label": "03.01.2026",
      "local_hour_label": "01:00",
      "local_label": "2026-01-03 01:00 czasu polskiego",
      "local_started_at": "2026-01-03T01:00:00+01:00",
      "local_timezone_label": "czasu polskiego",
      "month": 1,
      "playable": true,
      "state": "available",
      "status_label": null,
      "utc_label": "2026-01-03 00:00 UTC",
      "utc_started_at": "2026-01-03T00:00:00+00:00",
      "year": 2026
    },
    {
      "archive_status": "published",
      "completeness_ratio": 1.0,
      "day": 3,
      "hour": 2,
      "hourly_archive_id": 17593,
      "local_date_label": "03.01.2026",
      "local_hour_label": "02:00",
      "local_label": "2026-01-03 02:00 czasu polskiego",
      "local_started_at": "2026-01-03T02:00:00+01:00",
      "local_timezone_label": "czasu polskiego",
      "month": 1,
      "playable": true,
      "state": "available",
      "status_label": null,
      "utc_label": "2026-01-03 01:00 UTC",
      "utc_started_at": "2026-01-03T01:00:00+00:00",
      "year": 2026
    },
    {
      "archive_status": "published",
      "completeness_ratio": 1.0,
      "day": 3,
      "hour": 3,
      "hourly_archive_id": 17594,
      "local_date_label": "03.01.2026",
      "local_hour_label": "03:00",
      "local_label": "2026-01-03 03:00 czasu polskiego",
      "local_started_at": "2026-01-03T03:00:00+01:00",
      "local_timezone_label": "czasu polskiego",
      "month": 1,
      "playable": true,
      "state": "available",
      "status_label": null,
      "utc_label": "2026-01-03 02:00 UTC",
      "utc_started_at": "2026-01-03T02:00:00+00:00",
      "year": 2026
    },
    {
      "archive_status": "published",
      "completeness_ratio": 1.0,
      "day": 3,
      "hour": 4,
      "hourly_archive_id": 17595,
      "local_date_label": "03.01.2026",
      "local_hour_label": "04:00",
      "local_label": "2026-01-03 04:00 czasu polskiego",
      "local_started_at": "2026-01-03T04:00:00+01:00",
      "local_timezone_label": "czasu polskiego",
      "month": 1,
      "playable": true,
      "state": "available",
      "status_label": null,
      "utc_label": "2026-01-03 03:00 UTC",
      "utc_started_at": "2026-01-03T03:00:00+00:00",
      "year": 2026
    },
    {
      "archive_status": "published",
      "completeness_ratio": 1.0,
      "day": 3,
      "hour": 5,
      "hourly_archive_id": 17596,
      "local_date_label": "03.01.2026",
      "local_hour_label": "05:00",
      "local_label": "2026-01-03 05:00 czasu polskiego",
      "local_started_at": "2026-01-03T05:00:00+01:00",
      "local_timezone_label": "czasu polskiego",
      "month": 1,
      "playable": true,
      "state": "available",
      "status_label": null,
      "utc_label": "2026-01-03 04:00 UTC",
      "utc_started_at": "2026-01-03T04:00:00+00:00",
      "year": 2026
    },
    {
      "archive_status": "published",
      "completeness_ratio": 1.0,
      "day": 3,
      "hour": 6,
      "hourly_archive_id": 17597,
      "local_date_label": "03.01.2026",
      "local_hour_label": "06:00",
      "local_label": "2026-01-03 06:00 czasu polskiego",
      "local_started_at": "2026-01-03T06:00:00+01:00",
      "local_timezone_label": "czasu polskiego",
      "month": 1,
      "playable": true,
      "state": "available",
      "status_label": null,
      "utc_label": "2026-01-03 05:00 UTC",
      "utc_started_at": "2026-01-03T05:00:00+00:00",
      "year": 2026
    },
    {
      "archive_status": "published",
      "completeness_ratio": 1.0,
      "day": 3,
      "hour": 7,
      "hourly_archive_id": 17598,
      "local_date_label": "03.01.2026",
      "local_hour_label": "07:00",
      "local_label": "2026-01-03 07:00 czasu polskiego",
      "local_started_at": "2026-01-03T07:00:00+01:00",
      "local_timezone_label": "czasu polskiego",
      "month": 1,
      "playable": true,
      "state": "available",
      "status_label": null,
      "utc_label": "2026-01-03 06:00 UTC",
      "utc_started_at": "2026-01-03T06:00:00+00:00",
      "year": 2026
    },
    {
      "archive_status": "published",
      "completeness_ratio": 1.0,
      "day": 3,
      "hour": 8,
      "hourly_archive_id": 17599,
      "local_date_label": "03.01.2026",
      "local_hour_label": "08:00",
      "local_label": "2026-01-03 08:00 czasu polskiego",
      "local_started_at": "2026-01-03T08:00:00+01:00",
      "local_timezone_label": "czasu polskiego",
      "month": 1,
      "playable": true,
      "state": "available",
      "status_label": null,
      "utc_label": "2026-01-03 07:00 UTC",
      "utc_started_at": "2026-01-03T07:00:00+00:00",
      "year": 2026
    },
    {
      "archive_status": "published",
      "completeness_ratio": 1.0,
      "day": 3,
      "hour": 9,
      "hourly_archive_id": 17600,
      "local_date_label": "03.01.2026",
      "local_hour_label": "09:00",
      "local_label": "2026-01-03 09:00 czasu polskiego",
      "local_started_at": "2026-01-03T09:00:00+01:00",
      "local_timezone_label": "czasu polskiego",
      "month": 1,
      "playable": true,
      "state": "available",
      "status_label": null,
      "utc_label": "2026-01-03 08:00 UTC",
      "utc_started_at": "2026-01-03T08:00:00+00:00",
      "year": 2026
    },
    {
      "archive_status": "published",
      "completeness_ratio": 1.0,
      "day": 3,
      "hour": 10,
      "hourly_archive_id": 17601,
      "local_date_label": "03.01.2026",
      "local_hour_label": "10:00",
      "local_label": "2026-01-03 10:00 czasu polskiego",
      "local_started_at": "2026-01-03T10:00:00+01:00",
      "local_timezone_label": "czasu polskiego",
      "month": 1,
      "playable": true,
      "state": "available",
      "status_label": null,
      "utc_label": "2026-01-03 09:00 UTC",
      "utc_started_at": "2026-01-03T09:00:00+00:00",
      "year": 2026
    },
    {
      "archive_status": "published",
      "completeness_ratio": 1.0,
      "day": 3,
      "hour": 11,
      "hourly_archive_id": 17602,
      "local_date_label": "03.01.2026",
      "local_hour_label": "11:00",
      "local_label": "2026-01-03 11:00 czasu polskiego",
      "local_started_at": "2026-01-03T11:00:00+01:00",
      "local_timezone_label": "czasu polskiego",
      "month": 1,
      "playable": true,
      "state": "available",
      "status_label": null,
      "utc_label": "2026-01-03 10:00 UTC",
      "utc_started_at": "2026-01-03T10:00:00+00:00",
      "year": 2026
    },
    {
      "archive_status": "published",
      "completeness_ratio": 1.0,
      "day": 3,
      "hour": 12,
      "hourly_archive_id": 17603,
      "local_date_label": "03.01.2026",
      "local_hour_label": "12:00",
      "local_label": "2026-01-03 12:00 czasu polskiego",
      "local_started_at": "2026-01-03T12:00:00+01:00",
      "local_timezone_label": "czasu polskiego",
      "month": 1,
      "playable": true,
      "state": "available",
      "status_label": null,
      "utc_label": "2026-01-03 11:00 UTC",
      "utc_started_at": "2026-01-03T11:00:00+00:00",
      "year": 2026
    },
    {
      "archive_status": "published",
      "completeness_ratio": 1.0,
      "day": 3,
      "hour": 13,
      "hourly_archive_id": 17604,
      "local_date_label": "03.01.2026",
      "local_hour_label": "13:00",
      "local_label": "2026-01-03 13:00 czasu polskiego",
      "local_started_at": "2026-01-03T13:00:00+01:00",
      "local_timezone_label": "czasu polskiego",
      "month": 1,
      "playable": true,
      "state": "available",
      "status_label": null,
      "utc_label": "2026-01-03 12:00 UTC",
      "utc_started_at": "2026-01-03T12:00:00+00:00",
      "year": 2026
    },
    {
      "archive_status": "published",
      "completeness_ratio": 1.0,
      "day": 3,
      "hour": 14,
      "hourly_archive_id": 17605,
      "local_date_label": "03.01.2026",
      "local_hour_label": "14:00",
      "local_label": "2026-01-03 14:00 czasu polskiego",
      "local_started_at": "2026-01-03T14:00:00+01:00",
      "local_timezone_label": "czasu polskiego",
      "month": 1,
      "playable": true,
      "state": "available",
      "status_label": null,
      "utc_label": "2026-01-03 13:00 UTC",
      "utc_started_at": "2026-01-03T13:00:00+00:00",
      "year": 2026
    },
    {
      "archive_status": "published",
      "completeness_ratio": 1.0,
      "day": 3,
      "hour": 15,
      "hourly_archive_id": 17606,
      "local_date_label": "03.01.2026",
      "local_hour_label": "15:00",
      "local_label": "2026-01-03 15:00 czasu polskiego",
      "local_started_at": "2026-01-03T15:00:00+01:00",
      "local_timezone_label": "czasu polskiego",
      "month": 1,
      "playable": true,
      "state": "available",
      "status_label": null,
      "utc_label": "2026-01-03 14:00 UTC",
      "utc_started_at": "2026-01-03T14:00:00+00:00",
      "year": 2026
    },
    {
      "archive_status": "published",
      "completeness_ratio": 1.0,
      "day": 3,
      "hour": 16,
      "hourly_archive_id": 17607,
      "local_date_label": "03.01.2026",
      "local_hour_label": "16:00",
      "local_label": "2026-01-03 16:00 czasu polskiego",
      "local_started_at": "2026-01-03T16:00:00+01:00",
      "local_timezone_label": "czasu polskiego",
      "month": 1,
      "playable": true,
      "state": "available",
      "status_label": null,
      "utc_label": "2026-01-03 15:00 UTC",
      "utc_started_at": "2026-01-03T15:00:00+00:00",
      "year": 2026
    },
    {
      "archive_status": "published",
      "completeness_ratio": 1.0,
      "day": 3,
      "hour": 17,
      "hourly_archive_id": 17608,
      "local_date_label": "03.01.2026",
      "local_hour_label": "17:00",
      "local_label": "2026-01-03 17:00 czasu polskiego",
      "local_started_at": "2026-01-03T17:00:00+01:00",
      "local_timezone_label": "czasu polskiego",
      "month": 1,
      "playable": true,
      "state": "available",
      "status_label": null,
      "utc_label": "2026-01-03 16:00 UTC",
      "utc_started_at": "2026-01-03T16:00:00+00:00",
      "year": 2026
    },
    {
      "archive_status": "published",
      "completeness_ratio": 1.0,
      "day": 3,
      "hour": 18,
      "hourly_archive_id": 17609,
      "local_date_label": "03.01.2026",
      "local_hour_label": "18:00",
      "local_label": "2026-01-03 18:00 czasu polskiego",
      "local_started_at": "2026-01-03T18:00:00+01:00",
      "local_timezone_label": "czasu polskiego",
      "month": 1,
      "playable": true,
      "state": "available",
      "status_label": null,
      "utc_label": "2026-01-03 17:00 UTC",
      "utc_started_at": "2026-01-03T17:00:00+00:00",
      "year": 2026
    },
    {
      "archive_status": "published",
      "completeness_ratio": 1.0,
      "day": 3,
      "hour": 19,
      "hourly_archive_id": 17610,
      "local_date_label": "03.01.2026",
      "local_hour_label": "19:00",
      "local_label": "2026-01-03 19:00 czasu polskiego",
      "local_started_at": "2026-01-03T19:00:00+01:00",
      "local_timezone_label": "czasu polskiego",
      "month": 1,
      "playable": true,
      "state": "available",
      "status_label": null,
      "utc_label": "2026-01-03 18:00 UTC",
      "utc_started_at": "2026-01-03T18:00:00+00:00",
      "year": 2026
    },
    {
      "archive_status": "published",
      "completeness_ratio": 1.0,
      "day": 3,
      "hour": 20,
      "hourly_archive_id": 17611,
      "local_date_label": "03.01.2026",
      "local_hour_label": "20:00",
      "local_label": "2026-01-03 20:00 czasu polskiego",
      "local_started_at": "2026-01-03T20:00:00+01:00",
      "local_timezone_label": "czasu polskiego",
      "month": 1,
      "playable": true,
      "state": "available",
      "status_label": null,
      "utc_label": "2026-01-03 19:00 UTC",
      "utc_started_at": "2026-01-03T19:00:00+00:00",
      "year": 2026
    },
    {
      "archive_status": "published",
      "completeness_ratio": 0.208,
      "day": 3,
      "hour": 21,
      "hourly_archive_id": 17612,
      "local_date_label": "03.01.2026",
      "local_hour_label": "21:00",
      "local_label": "2026-01-03 21:00 czasu polskiego",
      "local_started_at": "2026-01-03T21:00:00+01:00",
      "local_timezone_label": "czasu polskiego",
      "month": 1,
      "playable": true,
      "state": "available",
      "status_label": null,
      "utc_label": "2026-01-03 20:00 UTC",
      "utc_started_at": "2026-01-03T20:00:00+00:00",
      "year": 2026
    },
    {
      "archive_status": "published",
      "completeness_ratio": 1.0,
      "day": 3,
      "hour": 22,
      "hourly_archive_id": 17613,
      "local_date_label": "03.01.2026",
      "local_hour_label": "22:00",
      "local_label": "2026-01-03 22:00 czasu polskiego",
      "local_started_at": "2026-01-03T22:00:00+01:00",
      "local_timezone_label": "czasu polskiego",
      "month": 1,
      "playable": true,
      "state": "available",
      "status_label": null,
      "utc_label": "2026-01-03 21:00 UTC",
      "utc_started_at": "2026-01-03T21:00:00+00:00",
      "year": 2026
    },
    {
      "archive_status": "published",
      "completeness_ratio": 1.0,
      "day": 3,
      "hour": 23,
      "hourly_archive_id": 17614,
      "local_date_label": "03.01.2026",
      "local_hour_label": "23:00",
      "local_label": "2026-01-03 23:00 czasu polskiego",
      "local_started_at": "2026-01-03T23:00:00+01:00",
      "local_timezone_label": "czasu polskiego",
      "month": 1,
      "playable": true,
      "state": "available",
      "status_label": null,
      "utc_label": "2026-01-03 22:00 UTC",
      "utc_started_at": "2026-01-03T22:00:00+00:00",
      "year": 2026
    }
  ],
  "latest_archive_hour_expected_station_count": 0,
  "latest_archive_hour_started_at": "2026-04-25T18:00:00+00:00",
  "month": 1,
  "published_at": "2026-04-25T19:53:05.580680+00:00",
  "station": {
    "archive_count": 4837,
    "display_name": "Program 3",
    "public_name": "Polskie Radio Program 3",
    "slug": "pr3",
    "timezone": "Europe/Warsaw"
  },
  "year": 2026
}
