{
  "archives": [
    {
      "archive_item_identifier": "wnet-2026-05-01",
      "audio_url": "https://archive.org/download/wnet-2026-05-01/wnet_2026-05-01T22-00-00Z.mp3",
      "completeness_ratio": 1.0,
      "day": 2,
      "download_url": "https://archive.org/download/wnet-2026-05-01/wnet_2026-05-01T22-00-00Z.mp3",
      "duration_seconds": 3599.987,
      "hour": 0,
      "hourly_archive_id": 36792,
      "local_date_label": "02.05.2026",
      "local_hour_label": "00:00",
      "local_label": "2026-05-02 00:00 czasu polskiego",
      "local_started_at": "2026-05-02T00:00:00+02:00",
      "local_timezone_label": "czasu polskiego",
      "month": 5,
      "published_at": "2026-05-01T23:44:14.283192+00:00",
      "published_local_label": "2026-05-02 01:44 czasu polskiego",
      "remote_filename": "wnet_2026-05-01T22-00-00Z.mp3",
      "station_slug": "wnet",
      "status": "published",
      "utc_label": "2026-05-01 22:00 UTC",
      "utc_started_at": "2026-05-01T22:00:00+00:00",
      "year": 2026
    },
    {
      "archive_item_identifier": "wnet-2026-05-01",
      "audio_url": "https://archive.org/download/wnet-2026-05-01/wnet_2026-05-01T23-00-00Z.mp3",
      "completeness_ratio": 1.0,
      "day": 2,
      "download_url": "https://archive.org/download/wnet-2026-05-01/wnet_2026-05-01T23-00-00Z.mp3",
      "duration_seconds": 3600.013,
      "hour": 1,
      "hourly_archive_id": 36859,
      "local_date_label": "02.05.2026",
      "local_hour_label": "01:00",
      "local_label": "2026-05-02 01:00 czasu polskiego",
      "local_started_at": "2026-05-02T01:00:00+02:00",
      "local_timezone_label": "czasu polskiego",
      "month": 5,
      "published_at": "2026-05-02T00:40:40.215132+00:00",
      "published_local_label": "2026-05-02 02:40 czasu polskiego",
      "remote_filename": "wnet_2026-05-01T23-00-00Z.mp3",
      "station_slug": "wnet",
      "status": "published",
      "utc_label": "2026-05-01 23:00 UTC",
      "utc_started_at": "2026-05-01T23:00:00+00:00",
      "year": 2026
    },
    {
      "archive_item_identifier": "wnet-2026-05-02",
      "audio_url": "https://archive.org/download/wnet-2026-05-02/wnet_2026-05-02T00-00-00Z.mp3",
      "completeness_ratio": 1.0,
      "day": 2,
      "download_url": "https://archive.org/download/wnet-2026-05-02/wnet_2026-05-02T00-00-00Z.mp3",
      "duration_seconds": 3599.987,
      "hour": 2,
      "hourly_archive_id": 36926,
      "local_date_label": "02.05.2026",
      "local_hour_label": "02:00",
      "local_label": "2026-05-02 02:00 czasu polskiego",
      "local_started_at": "2026-05-02T02:00:00+02:00",
      "local_timezone_label": "czasu polskiego",
      "month": 5,
      "published_at": "2026-05-02T01:50:47.490052+00:00",
      "published_local_label": "2026-05-02 03:50 czasu polskiego",
      "remote_filename": "wnet_2026-05-02T00-00-00Z.mp3",
      "station_slug": "wnet",
      "status": "published",
      "utc_label": "2026-05-02 00:00 UTC",
      "utc_started_at": "2026-05-02T00:00:00+00:00",
      "year": 2026
    },
    {
      "archive_item_identifier": "wnet-2026-05-02",
      "audio_url": "https://archive.org/download/wnet-2026-05-02/wnet_2026-05-02T01-00-00Z.mp3",
      "completeness_ratio": 1.0,
      "day": 2,
      "download_url": "https://archive.org/download/wnet-2026-05-02/wnet_2026-05-02T01-00-00Z.mp3",
      "duration_seconds": 3600.013,
      "hour": 3,
      "hourly_archive_id": 36991,
      "local_date_label": "02.05.2026",
      "local_hour_label": "03:00",
      "local_label": "2026-05-02 03:00 czasu polskiego",
      "local_started_at": "2026-05-02T03:00:00+02:00",
      "local_timezone_label": "czasu polskiego",
      "month": 5,
      "published_at": "2026-05-02T02:39:25.633976+00:00",
      "published_local_label": "2026-05-02 04:39 czasu polskiego",
      "remote_filename": "wnet_2026-05-02T01-00-00Z.mp3",
      "station_slug": "wnet",
      "status": "published",
      "utc_label": "2026-05-02 01:00 UTC",
      "utc_started_at": "2026-05-02T01:00:00+00:00",
      "year": 2026
    },
    {
      "archive_item_identifier": "wnet-2026-05-02",
      "audio_url": "https://archive.org/download/wnet-2026-05-02/wnet_2026-05-02T02-00-00Z.mp3",
      "completeness_ratio": 1.0,
      "day": 2,
      "download_url": "https://archive.org/download/wnet-2026-05-02/wnet_2026-05-02T02-00-00Z.mp3",
      "duration_seconds": 3600.065,
      "hour": 4,
      "hourly_archive_id": 37061,
      "local_date_label": "02.05.2026",
      "local_hour_label": "04:00",
      "local_label": "2026-05-02 04:00 czasu polskiego",
      "local_started_at": "2026-05-02T04:00:00+02:00",
      "local_timezone_label": "czasu polskiego",
      "month": 5,
      "published_at": "2026-05-02T03:38:59.230456+00:00",
      "published_local_label": "2026-05-02 05:38 czasu polskiego",
      "remote_filename": "wnet_2026-05-02T02-00-00Z.mp3",
      "station_slug": "wnet",
      "status": "published",
      "utc_label": "2026-05-02 02:00 UTC",
      "utc_started_at": "2026-05-02T02:00:00+00:00",
      "year": 2026
    },
    {
      "archive_item_identifier": "wnet-2026-05-02",
      "audio_url": "https://archive.org/download/wnet-2026-05-02/wnet_2026-05-02T03-00-00Z.mp3",
      "completeness_ratio": 1.0,
      "day": 2,
      "download_url": "https://archive.org/download/wnet-2026-05-02/wnet_2026-05-02T03-00-00Z.mp3",
      "duration_seconds": 3599.856,
      "hour": 5,
      "hourly_archive_id": 37127,
      "local_date_label": "02.05.2026",
      "local_hour_label": "05:00",
      "local_label": "2026-05-02 05:00 czasu polskiego",
      "local_started_at": "2026-05-02T05:00:00+02:00",
      "local_timezone_label": "czasu polskiego",
      "month": 5,
      "published_at": "2026-05-02T04:42:37.254014+00:00",
      "published_local_label": "2026-05-02 06:42 czasu polskiego",
      "remote_filename": "wnet_2026-05-02T03-00-00Z.mp3",
      "station_slug": "wnet",
      "status": "published",
      "utc_label": "2026-05-02 03:00 UTC",
      "utc_started_at": "2026-05-02T03:00:00+00:00",
      "year": 2026
    },
    {
      "archive_item_identifier": "wnet-2026-05-02",
      "audio_url": "https://archive.org/download/wnet-2026-05-02/wnet_2026-05-02T04-00-00Z.mp3",
      "completeness_ratio": 1.0,
      "day": 2,
      "download_url": "https://archive.org/download/wnet-2026-05-02/wnet_2026-05-02T04-00-00Z.mp3",
      "duration_seconds": 3600.065,
      "hour": 6,
      "hourly_archive_id": 37194,
      "local_date_label": "02.05.2026",
      "local_hour_label": "06:00",
      "local_label": "2026-05-02 06:00 czasu polskiego",
      "local_started_at": "2026-05-02T06:00:00+02:00",
      "local_timezone_label": "czasu polskiego",
      "month": 5,
      "published_at": "2026-05-02T05:35:23.039904+00:00",
      "published_local_label": "2026-05-02 07:35 czasu polskiego",
      "remote_filename": "wnet_2026-05-02T04-00-00Z.mp3",
      "station_slug": "wnet",
      "status": "published",
      "utc_label": "2026-05-02 04:00 UTC",
      "utc_started_at": "2026-05-02T04:00:00+00:00",
      "year": 2026
    },
    {
      "archive_item_identifier": "wnet-2026-05-02",
      "audio_url": "https://archive.org/download/wnet-2026-05-02/wnet_2026-05-02T05-00-00Z.mp3",
      "completeness_ratio": 1.0,
      "day": 2,
      "download_url": "https://archive.org/download/wnet-2026-05-02/wnet_2026-05-02T05-00-00Z.mp3",
      "duration_seconds": 3599.882,
      "hour": 7,
      "hourly_archive_id": 37261,
      "local_date_label": "02.05.2026",
      "local_hour_label": "07:00",
      "local_label": "2026-05-02 07:00 czasu polskiego",
      "local_started_at": "2026-05-02T07:00:00+02:00",
      "local_timezone_label": "czasu polskiego",
      "month": 5,
      "published_at": "2026-05-02T06:44:19.441188+00:00",
      "published_local_label": "2026-05-02 08:44 czasu polskiego",
      "remote_filename": "wnet_2026-05-02T05-00-00Z.mp3",
      "station_slug": "wnet",
      "status": "published",
      "utc_label": "2026-05-02 05:00 UTC",
      "utc_started_at": "2026-05-02T05:00:00+00:00",
      "year": 2026
    },
    {
      "archive_item_identifier": "wnet-2026-05-02",
      "audio_url": "https://archive.org/download/wnet-2026-05-02/wnet_2026-05-02T06-00-00Z.mp3",
      "completeness_ratio": 0.9997,
      "day": 2,
      "download_url": "https://archive.org/download/wnet-2026-05-02/wnet_2026-05-02T06-00-00Z.mp3",
      "duration_seconds": 3599.712,
      "hour": 8,
      "hourly_archive_id": 37328,
      "local_date_label": "02.05.2026",
      "local_hour_label": "08:00",
      "local_label": "2026-05-02 08:00 czasu polskiego",
      "local_started_at": "2026-05-02T08:00:00+02:00",
      "local_timezone_label": "czasu polskiego",
      "month": 5,
      "published_at": "2026-05-02T07:39:29.881613+00:00",
      "published_local_label": "2026-05-02 09:39 czasu polskiego",
      "remote_filename": "wnet_2026-05-02T06-00-00Z.mp3",
      "station_slug": "wnet",
      "status": "published",
      "utc_label": "2026-05-02 06:00 UTC",
      "utc_started_at": "2026-05-02T06:00:00+00:00",
      "year": 2026
    },
    {
      "archive_item_identifier": "wnet-2026-05-02",
      "audio_url": "https://archive.org/download/wnet-2026-05-02/wnet_2026-05-02T07-00-00Z.mp3",
      "completeness_ratio": 1.0,
      "day": 2,
      "download_url": "https://archive.org/download/wnet-2026-05-02/wnet_2026-05-02T07-00-00Z.mp3",
      "duration_seconds": 3599.987,
      "hour": 9,
      "hourly_archive_id": 37399,
      "local_date_label": "02.05.2026",
      "local_hour_label": "09:00",
      "local_label": "2026-05-02 09:00 czasu polskiego",
      "local_started_at": "2026-05-02T09:00:00+02:00",
      "local_timezone_label": "czasu polskiego",
      "month": 5,
      "published_at": "2026-05-02T08:45:54.377422+00:00",
      "published_local_label": "2026-05-02 10:45 czasu polskiego",
      "remote_filename": "wnet_2026-05-02T07-00-00Z.mp3",
      "station_slug": "wnet",
      "status": "published",
      "utc_label": "2026-05-02 07:00 UTC",
      "utc_started_at": "2026-05-02T07:00:00+00:00",
      "year": 2026
    },
    {
      "archive_item_identifier": "wnet-2026-05-02",
      "audio_url": "https://archive.org/download/wnet-2026-05-02/wnet_2026-05-02T08-00-00Z.mp3",
      "completeness_ratio": 1.0,
      "day": 2,
      "download_url": "https://archive.org/download/wnet-2026-05-02/wnet_2026-05-02T08-00-00Z.mp3",
      "duration_seconds": 3600.013,
      "hour": 10,
      "hourly_archive_id": 37468,
      "local_date_label": "02.05.2026",
      "local_hour_label": "10:00",
      "local_label": "2026-05-02 10:00 czasu polskiego",
      "local_started_at": "2026-05-02T10:00:00+02:00",
      "local_timezone_label": "czasu polskiego",
      "month": 5,
      "published_at": "2026-05-02T09:37:19.254257+00:00",
      "published_local_label": "2026-05-02 11:37 czasu polskiego",
      "remote_filename": "wnet_2026-05-02T08-00-00Z.mp3",
      "station_slug": "wnet",
      "status": "published",
      "utc_label": "2026-05-02 08:00 UTC",
      "utc_started_at": "2026-05-02T08:00:00+00:00",
      "year": 2026
    },
    {
      "archive_item_identifier": "wnet-2026-05-02",
      "audio_url": "https://archive.org/download/wnet-2026-05-02/wnet_2026-05-02T09-00-00Z.mp3",
      "completeness_ratio": 1.0,
      "day": 2,
      "download_url": "https://archive.org/download/wnet-2026-05-02/wnet_2026-05-02T09-00-00Z.mp3",
      "duration_seconds": 3599.987,
      "hour": 11,
      "hourly_archive_id": 37533,
      "local_date_label": "02.05.2026",
      "local_hour_label": "11:00",
      "local_label": "2026-05-02 11:00 czasu polskiego",
      "local_started_at": "2026-05-02T11:00:00+02:00",
      "local_timezone_label": "czasu polskiego",
      "month": 5,
      "published_at": "2026-05-02T10:38:27.205208+00:00",
      "published_local_label": "2026-05-02 12:38 czasu polskiego",
      "remote_filename": "wnet_2026-05-02T09-00-00Z.mp3",
      "station_slug": "wnet",
      "status": "published",
      "utc_label": "2026-05-02 09:00 UTC",
      "utc_started_at": "2026-05-02T09:00:00+00:00",
      "year": 2026
    },
    {
      "archive_item_identifier": "wnet-2026-05-02",
      "audio_url": "https://archive.org/download/wnet-2026-05-02/wnet_2026-05-02T10-00-00Z.mp3",
      "completeness_ratio": 1.0,
      "day": 2,
      "download_url": "https://archive.org/download/wnet-2026-05-02/wnet_2026-05-02T10-00-00Z.mp3",
      "duration_seconds": 3599.935,
      "hour": 12,
      "hourly_archive_id": 37600,
      "local_date_label": "02.05.2026",
      "local_hour_label": "12:00",
      "local_label": "2026-05-02 12:00 czasu polskiego",
      "local_started_at": "2026-05-02T12:00:00+02:00",
      "local_timezone_label": "czasu polskiego",
      "month": 5,
      "published_at": "2026-05-02T11:42:21.662383+00:00",
      "published_local_label": "2026-05-02 13:42 czasu polskiego",
      "remote_filename": "wnet_2026-05-02T10-00-00Z.mp3",
      "station_slug": "wnet",
      "status": "published",
      "utc_label": "2026-05-02 10:00 UTC",
      "utc_started_at": "2026-05-02T10:00:00+00:00",
      "year": 2026
    },
    {
      "archive_item_identifier": "wnet-2026-05-02",
      "audio_url": "https://archive.org/download/wnet-2026-05-02/wnet_2026-05-02T11-00-00Z.mp3",
      "completeness_ratio": 1.0,
      "day": 2,
      "download_url": "https://archive.org/download/wnet-2026-05-02/wnet_2026-05-02T11-00-00Z.mp3",
      "duration_seconds": 3600.144,
      "hour": 13,
      "hourly_archive_id": 37669,
      "local_date_label": "02.05.2026",
      "local_hour_label": "13:00",
      "local_label": "2026-05-02 13:00 czasu polskiego",
      "local_started_at": "2026-05-02T13:00:00+02:00",
      "local_timezone_label": "czasu polskiego",
      "month": 5,
      "published_at": "2026-05-02T12:42:09.404261+00:00",
      "published_local_label": "2026-05-02 14:42 czasu polskiego",
      "remote_filename": "wnet_2026-05-02T11-00-00Z.mp3",
      "station_slug": "wnet",
      "status": "published",
      "utc_label": "2026-05-02 11:00 UTC",
      "utc_started_at": "2026-05-02T11:00:00+00:00",
      "year": 2026
    },
    {
      "archive_item_identifier": "wnet-2026-05-02",
      "audio_url": "https://archive.org/download/wnet-2026-05-02/wnet_2026-05-02T12-00-00Z.mp3",
      "completeness_ratio": 1.0,
      "day": 2,
      "download_url": "https://archive.org/download/wnet-2026-05-02/wnet_2026-05-02T12-00-00Z.mp3",
      "duration_seconds": 3599.987,
      "hour": 14,
      "hourly_archive_id": 37736,
      "local_date_label": "02.05.2026",
      "local_hour_label": "14:00",
      "local_label": "2026-05-02 14:00 czasu polskiego",
      "local_started_at": "2026-05-02T14:00:00+02:00",
      "local_timezone_label": "czasu polskiego",
      "month": 5,
      "published_at": "2026-05-02T13:47:46.445328+00:00",
      "published_local_label": "2026-05-02 15:47 czasu polskiego",
      "remote_filename": "wnet_2026-05-02T12-00-00Z.mp3",
      "station_slug": "wnet",
      "status": "published",
      "utc_label": "2026-05-02 12:00 UTC",
      "utc_started_at": "2026-05-02T12:00:00+00:00",
      "year": 2026
    },
    {
      "archive_item_identifier": "wnet-2026-05-02",
      "audio_url": "https://archive.org/download/wnet-2026-05-02/wnet_2026-05-02T13-00-00Z.mp3",
      "completeness_ratio": 1.0,
      "day": 2,
      "download_url": "https://archive.org/download/wnet-2026-05-02/wnet_2026-05-02T13-00-00Z.mp3",
      "duration_seconds": 3599.935,
      "hour": 15,
      "hourly_archive_id": 37807,
      "local_date_label": "02.05.2026",
      "local_hour_label": "15:00",
      "local_label": "2026-05-02 15:00 czasu polskiego",
      "local_started_at": "2026-05-02T15:00:00+02:00",
      "local_timezone_label": "czasu polskiego",
      "month": 5,
      "published_at": "2026-05-02T14:46:37.343600+00:00",
      "published_local_label": "2026-05-02 16:46 czasu polskiego",
      "remote_filename": "wnet_2026-05-02T13-00-00Z.mp3",
      "station_slug": "wnet",
      "status": "published",
      "utc_label": "2026-05-02 13:00 UTC",
      "utc_started_at": "2026-05-02T13:00:00+00:00",
      "year": 2026
    },
    {
      "archive_item_identifier": "wnet-2026-05-02",
      "audio_url": "https://archive.org/download/wnet-2026-05-02/wnet_2026-05-02T14-00-00Z.mp3",
      "completeness_ratio": 1.0,
      "day": 2,
      "download_url": "https://archive.org/download/wnet-2026-05-02/wnet_2026-05-02T14-00-00Z.mp3",
      "duration_seconds": 3600.013,
      "hour": 16,
      "hourly_archive_id": 37864,
      "local_date_label": "02.05.2026",
      "local_hour_label": "16:00",
      "local_label": "2026-05-02 16:00 czasu polskiego",
      "local_started_at": "2026-05-02T16:00:00+02:00",
      "local_timezone_label": "czasu polskiego",
      "month": 5,
      "published_at": "2026-05-02T15:35:54.304288+00:00",
      "published_local_label": "2026-05-02 17:35 czasu polskiego",
      "remote_filename": "wnet_2026-05-02T14-00-00Z.mp3",
      "station_slug": "wnet",
      "status": "published",
      "utc_label": "2026-05-02 14:00 UTC",
      "utc_started_at": "2026-05-02T14:00:00+00:00",
      "year": 2026
    },
    {
      "archive_item_identifier": "wnet-2026-05-02",
      "audio_url": "https://archive.org/download/wnet-2026-05-02/wnet_2026-05-02T15-00-00Z.mp3",
      "completeness_ratio": 1.0,
      "day": 2,
      "download_url": "https://archive.org/download/wnet-2026-05-02/wnet_2026-05-02T15-00-00Z.mp3",
      "duration_seconds": 3599.987,
      "hour": 17,
      "hourly_archive_id": 37903,
      "local_date_label": "02.05.2026",
      "local_hour_label": "17:00",
      "local_label": "2026-05-02 17:00 czasu polskiego",
      "local_started_at": "2026-05-02T17:00:00+02:00",
      "local_timezone_label": "czasu polskiego",
      "month": 5,
      "published_at": "2026-05-02T16:34:24.472988+00:00",
      "published_local_label": "2026-05-02 18:34 czasu polskiego",
      "remote_filename": "wnet_2026-05-02T15-00-00Z.mp3",
      "station_slug": "wnet",
      "status": "published",
      "utc_label": "2026-05-02 15:00 UTC",
      "utc_started_at": "2026-05-02T15:00:00+00:00",
      "year": 2026
    },
    {
      "archive_item_identifier": "wnet-2026-05-02",
      "audio_url": "https://archive.org/download/wnet-2026-05-02/wnet_2026-05-02T16-00-00Z.mp3",
      "completeness_ratio": 1.0,
      "day": 2,
      "download_url": "https://archive.org/download/wnet-2026-05-02/wnet_2026-05-02T16-00-00Z.mp3",
      "duration_seconds": 3599.935,
      "hour": 18,
      "hourly_archive_id": 37942,
      "local_date_label": "02.05.2026",
      "local_hour_label": "18:00",
      "local_label": "2026-05-02 18:00 czasu polskiego",
      "local_started_at": "2026-05-02T18:00:00+02:00",
      "local_timezone_label": "czasu polskiego",
      "month": 5,
      "published_at": "2026-05-02T17:48:45.741712+00:00",
      "published_local_label": "2026-05-02 19:48 czasu polskiego",
      "remote_filename": "wnet_2026-05-02T16-00-00Z.mp3",
      "station_slug": "wnet",
      "status": "published",
      "utc_label": "2026-05-02 16:00 UTC",
      "utc_started_at": "2026-05-02T16:00:00+00:00",
      "year": 2026
    },
    {
      "archive_item_identifier": "wnet-2026-05-02",
      "audio_url": "https://archive.org/download/wnet-2026-05-02/wnet_2026-05-02T17-00-00Z.mp3",
      "completeness_ratio": 0.9997,
      "day": 2,
      "download_url": "https://archive.org/download/wnet-2026-05-02/wnet_2026-05-02T17-00-00Z.mp3",
      "duration_seconds": 3599.76,
      "hour": 19,
      "hourly_archive_id": 37981,
      "local_date_label": "02.05.2026",
      "local_hour_label": "19:00",
      "local_label": "2026-05-02 19:00 czasu polskiego",
      "local_started_at": "2026-05-02T19:00:00+02:00",
      "local_timezone_label": "czasu polskiego",
      "month": 5,
      "published_at": "2026-05-02T18:47:33.156490+00:00",
      "published_local_label": "2026-05-02 20:47 czasu polskiego",
      "remote_filename": "wnet_2026-05-02T17-00-00Z.mp3",
      "station_slug": "wnet",
      "status": "published",
      "utc_label": "2026-05-02 17:00 UTC",
      "utc_started_at": "2026-05-02T17:00:00+00:00",
      "year": 2026
    },
    {
      "archive_item_identifier": "wnet-2026-05-02",
      "audio_url": "https://archive.org/download/wnet-2026-05-02/wnet_2026-05-02T18-00-00Z.mp3",
      "completeness_ratio": 1.0,
      "day": 2,
      "download_url": "https://archive.org/download/wnet-2026-05-02/wnet_2026-05-02T18-00-00Z.mp3",
      "duration_seconds": 3599.987,
      "hour": 20,
      "hourly_archive_id": 38020,
      "local_date_label": "02.05.2026",
      "local_hour_label": "20:00",
      "local_label": "2026-05-02 20:00 czasu polskiego",
      "local_started_at": "2026-05-02T20:00:00+02:00",
      "local_timezone_label": "czasu polskiego",
      "month": 5,
      "published_at": "2026-05-02T19:39:13.388686+00:00",
      "published_local_label": "2026-05-02 21:39 czasu polskiego",
      "remote_filename": "wnet_2026-05-02T18-00-00Z.mp3",
      "station_slug": "wnet",
      "status": "published",
      "utc_label": "2026-05-02 18:00 UTC",
      "utc_started_at": "2026-05-02T18:00:00+00:00",
      "year": 2026
    },
    {
      "archive_item_identifier": "wnet-2026-05-02",
      "audio_url": "https://archive.org/download/wnet-2026-05-02/wnet_2026-05-02T19-00-00Z.mp3",
      "completeness_ratio": 1.0,
      "day": 2,
      "download_url": "https://archive.org/download/wnet-2026-05-02/wnet_2026-05-02T19-00-00Z.mp3",
      "duration_seconds": 3600.013,
      "hour": 21,
      "hourly_archive_id": 38059,
      "local_date_label": "02.05.2026",
      "local_hour_label": "21:00",
      "local_label": "2026-05-02 21:00 czasu polskiego",
      "local_started_at": "2026-05-02T21:00:00+02:00",
      "local_timezone_label": "czasu polskiego",
      "month": 5,
      "published_at": "2026-05-02T20:32:34.586217+00:00",
      "published_local_label": "2026-05-02 22:32 czasu polskiego",
      "remote_filename": "wnet_2026-05-02T19-00-00Z.mp3",
      "station_slug": "wnet",
      "status": "published",
      "utc_label": "2026-05-02 19:00 UTC",
      "utc_started_at": "2026-05-02T19:00:00+00:00",
      "year": 2026
    },
    {
      "archive_item_identifier": "wnet-2026-05-02",
      "audio_url": "https://archive.org/download/wnet-2026-05-02/wnet_2026-05-02T20-00-00Z.mp3",
      "completeness_ratio": 1.0,
      "day": 2,
      "download_url": "https://archive.org/download/wnet-2026-05-02/wnet_2026-05-02T20-00-00Z.mp3",
      "duration_seconds": 3600.065,
      "hour": 22,
      "hourly_archive_id": 38098,
      "local_date_label": "02.05.2026",
      "local_hour_label": "22:00",
      "local_label": "2026-05-02 22:00 czasu polskiego",
      "local_started_at": "2026-05-02T22:00:00+02:00",
      "local_timezone_label": "czasu polskiego",
      "month": 5,
      "published_at": "2026-05-02T21:35:23.894493+00:00",
      "published_local_label": "2026-05-02 23:35 czasu polskiego",
      "remote_filename": "wnet_2026-05-02T20-00-00Z.mp3",
      "station_slug": "wnet",
      "status": "published",
      "utc_label": "2026-05-02 20:00 UTC",
      "utc_started_at": "2026-05-02T20:00:00+00:00",
      "year": 2026
    },
    {
      "archive_item_identifier": "wnet-2026-05-02",
      "audio_url": "https://archive.org/download/wnet-2026-05-02/wnet_2026-05-02T21-00-00Z.mp3",
      "completeness_ratio": 0.8514,
      "day": 2,
      "download_url": "https://archive.org/download/wnet-2026-05-02/wnet_2026-05-02T21-00-00Z.mp3",
      "duration_seconds": 3599.544,
      "hour": 23,
      "hourly_archive_id": 38175,
      "local_date_label": "02.05.2026",
      "local_hour_label": "23:00",
      "local_label": "2026-05-02 23:00 czasu polskiego",
      "local_started_at": "2026-05-02T23:00:00+02:00",
      "local_timezone_label": "czasu polskiego",
      "month": 5,
      "published_at": "2026-05-02T22:58:22.342437+00:00",
      "published_local_label": "2026-05-03 00:58 czasu polskiego",
      "remote_filename": "wnet_2026-05-02T21-00-00Z.mp3",
      "station_slug": "wnet",
      "status": "published",
      "utc_label": "2026-05-02 21:00 UTC",
      "utc_started_at": "2026-05-02T21:00:00+00:00",
      "year": 2026
    }
  ],
  "day": 2,
  "generated_at": "2026-05-03T01:49:50.314832+00:00",
  "hour_slots": [
    {
      "archive_status": "published",
      "completeness_ratio": 1.0,
      "day": 2,
      "hour": 0,
      "hourly_archive_id": 36792,
      "local_date_label": "02.05.2026",
      "local_hour_label": "00:00",
      "local_label": "2026-05-02 00:00 czasu polskiego",
      "local_started_at": "2026-05-02T00:00:00+02:00",
      "local_timezone_label": "czasu polskiego",
      "month": 5,
      "playable": true,
      "state": "available",
      "status_label": null,
      "utc_label": "2026-05-01 22:00 UTC",
      "utc_started_at": "2026-05-01T22:00:00+00:00",
      "year": 2026
    },
    {
      "archive_status": "published",
      "completeness_ratio": 1.0,
      "day": 2,
      "hour": 1,
      "hourly_archive_id": 36859,
      "local_date_label": "02.05.2026",
      "local_hour_label": "01:00",
      "local_label": "2026-05-02 01:00 czasu polskiego",
      "local_started_at": "2026-05-02T01:00:00+02:00",
      "local_timezone_label": "czasu polskiego",
      "month": 5,
      "playable": true,
      "state": "available",
      "status_label": null,
      "utc_label": "2026-05-01 23:00 UTC",
      "utc_started_at": "2026-05-01T23:00:00+00:00",
      "year": 2026
    },
    {
      "archive_status": "published",
      "completeness_ratio": 1.0,
      "day": 2,
      "hour": 2,
      "hourly_archive_id": 36926,
      "local_date_label": "02.05.2026",
      "local_hour_label": "02:00",
      "local_label": "2026-05-02 02:00 czasu polskiego",
      "local_started_at": "2026-05-02T02:00:00+02:00",
      "local_timezone_label": "czasu polskiego",
      "month": 5,
      "playable": true,
      "state": "available",
      "status_label": null,
      "utc_label": "2026-05-02 00:00 UTC",
      "utc_started_at": "2026-05-02T00:00:00+00:00",
      "year": 2026
    },
    {
      "archive_status": "published",
      "completeness_ratio": 1.0,
      "day": 2,
      "hour": 3,
      "hourly_archive_id": 36991,
      "local_date_label": "02.05.2026",
      "local_hour_label": "03:00",
      "local_label": "2026-05-02 03:00 czasu polskiego",
      "local_started_at": "2026-05-02T03:00:00+02:00",
      "local_timezone_label": "czasu polskiego",
      "month": 5,
      "playable": true,
      "state": "available",
      "status_label": null,
      "utc_label": "2026-05-02 01:00 UTC",
      "utc_started_at": "2026-05-02T01:00:00+00:00",
      "year": 2026
    },
    {
      "archive_status": "published",
      "completeness_ratio": 1.0,
      "day": 2,
      "hour": 4,
      "hourly_archive_id": 37061,
      "local_date_label": "02.05.2026",
      "local_hour_label": "04:00",
      "local_label": "2026-05-02 04:00 czasu polskiego",
      "local_started_at": "2026-05-02T04:00:00+02:00",
      "local_timezone_label": "czasu polskiego",
      "month": 5,
      "playable": true,
      "state": "available",
      "status_label": null,
      "utc_label": "2026-05-02 02:00 UTC",
      "utc_started_at": "2026-05-02T02:00:00+00:00",
      "year": 2026
    },
    {
      "archive_status": "published",
      "completeness_ratio": 1.0,
      "day": 2,
      "hour": 5,
      "hourly_archive_id": 37127,
      "local_date_label": "02.05.2026",
      "local_hour_label": "05:00",
      "local_label": "2026-05-02 05:00 czasu polskiego",
      "local_started_at": "2026-05-02T05:00:00+02:00",
      "local_timezone_label": "czasu polskiego",
      "month": 5,
      "playable": true,
      "state": "available",
      "status_label": null,
      "utc_label": "2026-05-02 03:00 UTC",
      "utc_started_at": "2026-05-02T03:00:00+00:00",
      "year": 2026
    },
    {
      "archive_status": "published",
      "completeness_ratio": 1.0,
      "day": 2,
      "hour": 6,
      "hourly_archive_id": 37194,
      "local_date_label": "02.05.2026",
      "local_hour_label": "06:00",
      "local_label": "2026-05-02 06:00 czasu polskiego",
      "local_started_at": "2026-05-02T06:00:00+02:00",
      "local_timezone_label": "czasu polskiego",
      "month": 5,
      "playable": true,
      "state": "available",
      "status_label": null,
      "utc_label": "2026-05-02 04:00 UTC",
      "utc_started_at": "2026-05-02T04:00:00+00:00",
      "year": 2026
    },
    {
      "archive_status": "published",
      "completeness_ratio": 1.0,
      "day": 2,
      "hour": 7,
      "hourly_archive_id": 37261,
      "local_date_label": "02.05.2026",
      "local_hour_label": "07:00",
      "local_label": "2026-05-02 07:00 czasu polskiego",
      "local_started_at": "2026-05-02T07:00:00+02:00",
      "local_timezone_label": "czasu polskiego",
      "month": 5,
      "playable": true,
      "state": "available",
      "status_label": null,
      "utc_label": "2026-05-02 05:00 UTC",
      "utc_started_at": "2026-05-02T05:00:00+00:00",
      "year": 2026
    },
    {
      "archive_status": "published",
      "completeness_ratio": 0.9997,
      "day": 2,
      "hour": 8,
      "hourly_archive_id": 37328,
      "local_date_label": "02.05.2026",
      "local_hour_label": "08:00",
      "local_label": "2026-05-02 08:00 czasu polskiego",
      "local_started_at": "2026-05-02T08:00:00+02:00",
      "local_timezone_label": "czasu polskiego",
      "month": 5,
      "playable": true,
      "state": "available",
      "status_label": null,
      "utc_label": "2026-05-02 06:00 UTC",
      "utc_started_at": "2026-05-02T06:00:00+00:00",
      "year": 2026
    },
    {
      "archive_status": "published",
      "completeness_ratio": 1.0,
      "day": 2,
      "hour": 9,
      "hourly_archive_id": 37399,
      "local_date_label": "02.05.2026",
      "local_hour_label": "09:00",
      "local_label": "2026-05-02 09:00 czasu polskiego",
      "local_started_at": "2026-05-02T09:00:00+02:00",
      "local_timezone_label": "czasu polskiego",
      "month": 5,
      "playable": true,
      "state": "available",
      "status_label": null,
      "utc_label": "2026-05-02 07:00 UTC",
      "utc_started_at": "2026-05-02T07:00:00+00:00",
      "year": 2026
    },
    {
      "archive_status": "published",
      "completeness_ratio": 1.0,
      "day": 2,
      "hour": 10,
      "hourly_archive_id": 37468,
      "local_date_label": "02.05.2026",
      "local_hour_label": "10:00",
      "local_label": "2026-05-02 10:00 czasu polskiego",
      "local_started_at": "2026-05-02T10:00:00+02:00",
      "local_timezone_label": "czasu polskiego",
      "month": 5,
      "playable": true,
      "state": "available",
      "status_label": null,
      "utc_label": "2026-05-02 08:00 UTC",
      "utc_started_at": "2026-05-02T08:00:00+00:00",
      "year": 2026
    },
    {
      "archive_status": "published",
      "completeness_ratio": 1.0,
      "day": 2,
      "hour": 11,
      "hourly_archive_id": 37533,
      "local_date_label": "02.05.2026",
      "local_hour_label": "11:00",
      "local_label": "2026-05-02 11:00 czasu polskiego",
      "local_started_at": "2026-05-02T11:00:00+02:00",
      "local_timezone_label": "czasu polskiego",
      "month": 5,
      "playable": true,
      "state": "available",
      "status_label": null,
      "utc_label": "2026-05-02 09:00 UTC",
      "utc_started_at": "2026-05-02T09:00:00+00:00",
      "year": 2026
    },
    {
      "archive_status": "published",
      "completeness_ratio": 1.0,
      "day": 2,
      "hour": 12,
      "hourly_archive_id": 37600,
      "local_date_label": "02.05.2026",
      "local_hour_label": "12:00",
      "local_label": "2026-05-02 12:00 czasu polskiego",
      "local_started_at": "2026-05-02T12:00:00+02:00",
      "local_timezone_label": "czasu polskiego",
      "month": 5,
      "playable": true,
      "state": "available",
      "status_label": null,
      "utc_label": "2026-05-02 10:00 UTC",
      "utc_started_at": "2026-05-02T10:00:00+00:00",
      "year": 2026
    },
    {
      "archive_status": "published",
      "completeness_ratio": 1.0,
      "day": 2,
      "hour": 13,
      "hourly_archive_id": 37669,
      "local_date_label": "02.05.2026",
      "local_hour_label": "13:00",
      "local_label": "2026-05-02 13:00 czasu polskiego",
      "local_started_at": "2026-05-02T13:00:00+02:00",
      "local_timezone_label": "czasu polskiego",
      "month": 5,
      "playable": true,
      "state": "available",
      "status_label": null,
      "utc_label": "2026-05-02 11:00 UTC",
      "utc_started_at": "2026-05-02T11:00:00+00:00",
      "year": 2026
    },
    {
      "archive_status": "published",
      "completeness_ratio": 1.0,
      "day": 2,
      "hour": 14,
      "hourly_archive_id": 37736,
      "local_date_label": "02.05.2026",
      "local_hour_label": "14:00",
      "local_label": "2026-05-02 14:00 czasu polskiego",
      "local_started_at": "2026-05-02T14:00:00+02:00",
      "local_timezone_label": "czasu polskiego",
      "month": 5,
      "playable": true,
      "state": "available",
      "status_label": null,
      "utc_label": "2026-05-02 12:00 UTC",
      "utc_started_at": "2026-05-02T12:00:00+00:00",
      "year": 2026
    },
    {
      "archive_status": "published",
      "completeness_ratio": 1.0,
      "day": 2,
      "hour": 15,
      "hourly_archive_id": 37807,
      "local_date_label": "02.05.2026",
      "local_hour_label": "15:00",
      "local_label": "2026-05-02 15:00 czasu polskiego",
      "local_started_at": "2026-05-02T15:00:00+02:00",
      "local_timezone_label": "czasu polskiego",
      "month": 5,
      "playable": true,
      "state": "available",
      "status_label": null,
      "utc_label": "2026-05-02 13:00 UTC",
      "utc_started_at": "2026-05-02T13:00:00+00:00",
      "year": 2026
    },
    {
      "archive_status": "published",
      "completeness_ratio": 1.0,
      "day": 2,
      "hour": 16,
      "hourly_archive_id": 37864,
      "local_date_label": "02.05.2026",
      "local_hour_label": "16:00",
      "local_label": "2026-05-02 16:00 czasu polskiego",
      "local_started_at": "2026-05-02T16:00:00+02:00",
      "local_timezone_label": "czasu polskiego",
      "month": 5,
      "playable": true,
      "state": "available",
      "status_label": null,
      "utc_label": "2026-05-02 14:00 UTC",
      "utc_started_at": "2026-05-02T14:00:00+00:00",
      "year": 2026
    },
    {
      "archive_status": "published",
      "completeness_ratio": 1.0,
      "day": 2,
      "hour": 17,
      "hourly_archive_id": 37903,
      "local_date_label": "02.05.2026",
      "local_hour_label": "17:00",
      "local_label": "2026-05-02 17:00 czasu polskiego",
      "local_started_at": "2026-05-02T17:00:00+02:00",
      "local_timezone_label": "czasu polskiego",
      "month": 5,
      "playable": true,
      "state": "available",
      "status_label": null,
      "utc_label": "2026-05-02 15:00 UTC",
      "utc_started_at": "2026-05-02T15:00:00+00:00",
      "year": 2026
    },
    {
      "archive_status": "published",
      "completeness_ratio": 1.0,
      "day": 2,
      "hour": 18,
      "hourly_archive_id": 37942,
      "local_date_label": "02.05.2026",
      "local_hour_label": "18:00",
      "local_label": "2026-05-02 18:00 czasu polskiego",
      "local_started_at": "2026-05-02T18:00:00+02:00",
      "local_timezone_label": "czasu polskiego",
      "month": 5,
      "playable": true,
      "state": "available",
      "status_label": null,
      "utc_label": "2026-05-02 16:00 UTC",
      "utc_started_at": "2026-05-02T16:00:00+00:00",
      "year": 2026
    },
    {
      "archive_status": "published",
      "completeness_ratio": 0.9997,
      "day": 2,
      "hour": 19,
      "hourly_archive_id": 37981,
      "local_date_label": "02.05.2026",
      "local_hour_label": "19:00",
      "local_label": "2026-05-02 19:00 czasu polskiego",
      "local_started_at": "2026-05-02T19:00:00+02:00",
      "local_timezone_label": "czasu polskiego",
      "month": 5,
      "playable": true,
      "state": "available",
      "status_label": null,
      "utc_label": "2026-05-02 17:00 UTC",
      "utc_started_at": "2026-05-02T17:00:00+00:00",
      "year": 2026
    },
    {
      "archive_status": "published",
      "completeness_ratio": 1.0,
      "day": 2,
      "hour": 20,
      "hourly_archive_id": 38020,
      "local_date_label": "02.05.2026",
      "local_hour_label": "20:00",
      "local_label": "2026-05-02 20:00 czasu polskiego",
      "local_started_at": "2026-05-02T20:00:00+02:00",
      "local_timezone_label": "czasu polskiego",
      "month": 5,
      "playable": true,
      "state": "available",
      "status_label": null,
      "utc_label": "2026-05-02 18:00 UTC",
      "utc_started_at": "2026-05-02T18:00:00+00:00",
      "year": 2026
    },
    {
      "archive_status": "published",
      "completeness_ratio": 1.0,
      "day": 2,
      "hour": 21,
      "hourly_archive_id": 38059,
      "local_date_label": "02.05.2026",
      "local_hour_label": "21:00",
      "local_label": "2026-05-02 21:00 czasu polskiego",
      "local_started_at": "2026-05-02T21:00:00+02:00",
      "local_timezone_label": "czasu polskiego",
      "month": 5,
      "playable": true,
      "state": "available",
      "status_label": null,
      "utc_label": "2026-05-02 19:00 UTC",
      "utc_started_at": "2026-05-02T19:00:00+00:00",
      "year": 2026
    },
    {
      "archive_status": "published",
      "completeness_ratio": 1.0,
      "day": 2,
      "hour": 22,
      "hourly_archive_id": 38098,
      "local_date_label": "02.05.2026",
      "local_hour_label": "22:00",
      "local_label": "2026-05-02 22:00 czasu polskiego",
      "local_started_at": "2026-05-02T22:00:00+02:00",
      "local_timezone_label": "czasu polskiego",
      "month": 5,
      "playable": true,
      "state": "available",
      "status_label": null,
      "utc_label": "2026-05-02 20:00 UTC",
      "utc_started_at": "2026-05-02T20:00:00+00:00",
      "year": 2026
    },
    {
      "archive_status": "published",
      "completeness_ratio": 0.8514,
      "day": 2,
      "hour": 23,
      "hourly_archive_id": 38175,
      "local_date_label": "02.05.2026",
      "local_hour_label": "23:00",
      "local_label": "2026-05-02 23:00 czasu polskiego",
      "local_started_at": "2026-05-02T23:00:00+02:00",
      "local_timezone_label": "czasu polskiego",
      "month": 5,
      "playable": true,
      "state": "available",
      "status_label": null,
      "utc_label": "2026-05-02 21:00 UTC",
      "utc_started_at": "2026-05-02T21:00:00+00:00",
      "year": 2026
    }
  ],
  "latest_archive_hour_expected_station_count": 0,
  "latest_archive_hour_started_at": "2026-05-03T00:00:00+00:00",
  "month": 5,
  "published_at": "2026-05-03T01:49:50.314832+00:00",
  "station": {
    "archive_count": 799,
    "display_name": "Radio Wnet",
    "public_name": "Radio Wnet",
    "slug": "wnet",
    "timezone": "Europe/Warsaw"
  },
  "year": 2026
}
